// class version 51.0 (51)
// access flags 0x21
public class com/josecambronero/ObjectTagExamples implements edu/columbia/cs/psl/phosphor/struct/TaintedWithObjTag  {


  @Ledu/columbia/cs/psl/phosphor/runtime/TaintInstrumented;() // invisible
  // compiled from: ObjectTagExamples.java
  // access flags 0x9
  public static INNERCLASS edu/columbia/cs/psl/phosphor/struct/LinkedList$Node edu/columbia/cs/psl/phosphor/struct/LinkedList Node

  // access flags 0x1018
  final static synthetic Z $assertionsDisabled

  // access flags 0x1
  public <init>()V
   L0
   L1
    NEW edu/columbia/cs/psl/phosphor/struct/ControlTaintTagStack
    DUP
    BIPUSH 0
    INVOKESPECIAL edu/columbia/cs/psl/phosphor/struct/ControlTaintTagStack.<init> (I)V
    ASTORE 1
   L2
   L3
   L4
    LINENUMBER 12 L4
    ALOAD 0
    INVOKESPECIAL java/lang/Object.<init> ()V
    RETURN
   L5
    LOCALVARIABLE this Lcom/josecambronero/ObjectTagExamples; L4 L5 0
   L6
    LOCALVARIABLE phosphorJumpControlTag0 Ledu/columbia/cs/psl/phosphor/struct/ControlTaintTagStack; L1 L6 1
    MAXSTACK = 101
    MAXLOCALS = 2

  // access flags 0x9
  public static identity(Ljava/lang/Object;)Ljava/lang/Object;
   L0
   L1
    NEW edu/columbia/cs/psl/phosphor/struct/ControlTaintTagStack
    DUP
    BIPUSH 0
    INVOKESPECIAL edu/columbia/cs/psl/phosphor/struct/ControlTaintTagStack.<init> (I)V
    ASTORE 1
   L2
   L3
   L4
    LINENUMBER 15 L4
    ALOAD 0
    ARETURN
   L5
    LOCALVARIABLE o Ljava/lang/Object; L4 L5 0
   L6
    LOCALVARIABLE phosphorJumpControlTag0 Ledu/columbia/cs/psl/phosphor/struct/ControlTaintTagStack; L1 L6 1
    MAXSTACK = 101
    MAXLOCALS = 2

  // access flags 0x9
  public static testExample1()V
   L0
   L1
    NEW edu/columbia/cs/psl/phosphor/struct/ControlTaintTagStack
    DUP
    BIPUSH 2
    INVOKESPECIAL edu/columbia/cs/psl/phosphor/struct/ControlTaintTagStack.<init> (I)V
    ASTORE 0
    ACONST_NULL
    ASTORE 1
    ACONST_NULL
    ASTORE 2
   L2
   L3
    NEW edu/columbia/cs/psl/phosphor/struct/TaintedIntWithObjTag
    DUP
    INVOKESPECIAL edu/columbia/cs/psl/phosphor/struct/TaintedIntWithObjTag.<init> ()V
    ASTORE 3
   L4
   L5
    LINENUMBER 22 L5
    ALOAD 0
    INVOKEVIRTUAL edu/columbia/cs/psl/phosphor/struct/ControlTaintTagStack.copyTag ()Ledu/columbia/cs/psl/phosphor/runtime/Taint;
    BIPUSH 100
    LDC "source 1"
    ALOAD 3
    INVOKESTATIC edu/columbia/cs/psl/phosphor/runtime/MultiTainter.taintedInt$$PHOSPHORTAGGED (Ledu/columbia/cs/psl/phosphor/runtime/Taint;ILjava/lang/Object;Ledu/columbia/cs/psl/phosphor/struct/TaintedIntWithObjTag;)Ledu/columbia/cs/psl/phosphor/struct/TaintedIntWithObjTag;
    DUP
    GETFIELD edu/columbia/cs/psl/phosphor/struct/TaintedIntWithObjTag.taint : Ledu/columbia/cs/psl/phosphor/runtime/Taint;
    SWAP
    GETFIELD edu/columbia/cs/psl/phosphor/struct/TaintedIntWithObjTag.val : I
    SWAP
    ALOAD 0
    INVOKESTATIC edu/columbia/cs/psl/phosphor/runtime/Taint.combineTags (Ledu/columbia/cs/psl/phosphor/runtime/Taint;Ledu/columbia/cs/psl/phosphor/struct/ControlTaintTagStack;)Ledu/columbia/cs/psl/phosphor/runtime/Taint;
    SWAP
   L6
    ISTORE 4
    INVOKESTATIC edu/columbia/cs/psl/phosphor/runtime/Taint.copyTaint (Ledu/columbia/cs/psl/phosphor/runtime/Taint;)Ledu/columbia/cs/psl/phosphor/runtime/Taint;
    ASTORE 5
   L7
    LINENUMBER 25 L7
    ALOAD 0
    INVOKEVIRTUAL edu/columbia/cs/psl/phosphor/struct/ControlTaintTagStack.copyTag ()Ledu/columbia/cs/psl/phosphor/runtime/Taint;
    BIPUSH 100
   L8
    NEW edu/columbia/cs/psl/phosphor/runtime/Taint
    DUP
    LDC "source 2"
    INVOKESPECIAL edu/columbia/cs/psl/phosphor/runtime/Taint.<init> (Ljava/lang/Object;)V
    ALOAD 3
    INVOKESTATIC edu/columbia/cs/psl/phosphor/runtime/MultiTainter.taintedInt$$PHOSPHORTAGGED (Ledu/columbia/cs/psl/phosphor/runtime/Taint;ILjava/lang/Object;Ledu/columbia/cs/psl/phosphor/struct/TaintedIntWithObjTag;)Ledu/columbia/cs/psl/phosphor/struct/TaintedIntWithObjTag;
    DUP
    GETFIELD edu/columbia/cs/psl/phosphor/struct/TaintedIntWithObjTag.taint : Ledu/columbia/cs/psl/phosphor/runtime/Taint;
    SWAP
    GETFIELD edu/columbia/cs/psl/phosphor/struct/TaintedIntWithObjTag.val : I
    SWAP
    ALOAD 0
    INVOKESTATIC edu/columbia/cs/psl/phosphor/runtime/Taint.combineTags (Ledu/columbia/cs/psl/phosphor/runtime/Taint;Ledu/columbia/cs/psl/phosphor/struct/ControlTaintTagStack;)Ledu/columbia/cs/psl/phosphor/runtime/Taint;
    SWAP
   L9
    ISTORE 6
    INVOKESTATIC edu/columbia/cs/psl/phosphor/runtime/Taint.copyTaint (Ledu/columbia/cs/psl/phosphor/runtime/Taint;)Ledu/columbia/cs/psl/phosphor/runtime/Taint;
    ASTORE 7
   L10
    LINENUMBER 27 L10
   L11
    ALOAD 5
    ILOAD 4
   L12
    ALOAD 7
    ILOAD 6
   L13
    ISTORE 8
    SWAP
    ILOAD 8
   L14
    IADD
    DUP_X2
    POP
    INVOKESTATIC edu/columbia/cs/psl/phosphor/runtime/Taint.combineTags (Ledu/columbia/cs/psl/phosphor/runtime/Taint;Ledu/columbia/cs/psl/phosphor/runtime/Taint;)Ledu/columbia/cs/psl/phosphor/runtime/Taint;
    SWAP
    SWAP
    ALOAD 0
    INVOKESTATIC edu/columbia/cs/psl/phosphor/runtime/Taint.combineTags (Ledu/columbia/cs/psl/phosphor/runtime/Taint;Ledu/columbia/cs/psl/phosphor/struct/ControlTaintTagStack;)Ledu/columbia/cs/psl/phosphor/runtime/Taint;
    SWAP
   L15
    ISTORE 9
    INVOKESTATIC edu/columbia/cs/psl/phosphor/runtime/Taint.copyTaint (Ledu/columbia/cs/psl/phosphor/runtime/Taint;)Ledu/columbia/cs/psl/phosphor/runtime/Taint;
    ASTORE 10
   L16
    LINENUMBER 28 L16
   L17
    ALOAD 10
    ILOAD 9
    INVOKESTATIC edu/columbia/cs/psl/phosphor/runtime/MultiTainter.getTaint$$PHOSPHORTAGGED (Ledu/columbia/cs/psl/phosphor/runtime/Taint;I)Ledu/columbia/cs/psl/phosphor/runtime/Taint;
    ASTORE 11
   L18
    LINENUMBER 29 L18
    GETSTATIC com/josecambronero/ObjectTagExamples.$assertionsDisabledPHOSPHOR_TAG : Ledu/columbia/cs/psl/phosphor/runtime/Taint;
    GETSTATIC com/josecambronero/ObjectTagExamples.$assertionsDisabled : Z
    DUP
    INVOKESTATIC edu/ucdavis/cs/cyberlab/BBPhosphor/util/TaintHelper.saveTaint (Ljava/lang/Object;)V
    LDC "hello i coupied this! branching counting 1"
    INVOKESTATIC edu/ucdavis/cs/cyberlab/BBPhosphor/util/TaintHelper.printx (Ljava/lang/String;)V
    SWAP
    ALOAD 0
    SWAP
    ALOAD 1
    INVOKEVIRTUAL edu/columbia/cs/psl/phosphor/struct/ControlTaintTagStack.push (Ledu/columbia/cs/psl/phosphor/runtime/Taint;Ledu/columbia/cs/psl/phosphor/struct/EnqueuedTaint;)Ledu/columbia/cs/psl/phosphor/struct/EnqueuedTaint;
    ASTORE 1
    IFNE L19
   L20
    ALOAD 11
    IFNONNULL L19
   L21
   L22
    NEW java/lang/AssertionError
    DUP
    INVOKESPECIAL java/lang/AssertionError.<init> ()V
    DUP
    ALOAD 0
    INVOKESTATIC edu/columbia/cs/psl/phosphor/runtime/Taint.combineTagsOnObject (Ljava/lang/Object;Ledu/columbia/cs/psl/phosphor/struct/ControlTaintTagStack;)V
    ALOAD 0
    ALOAD 1
    INVOKEVIRTUAL edu/columbia/cs/psl/phosphor/struct/ControlTaintTagStack.pop (Ledu/columbia/cs/psl/phosphor/struct/EnqueuedTaint;)V
    ALOAD 0
    ALOAD 2
    INVOKEVIRTUAL edu/columbia/cs/psl/phosphor/struct/ControlTaintTagStack.pop (Ledu/columbia/cs/psl/phosphor/struct/EnqueuedTaint;)V
    ATHROW
   L19
    LINENUMBER 30 L19
   FRAME FULL [edu/columbia/cs/psl/phosphor/struct/ControlTaintTagStack edu/columbia/cs/psl/phosphor/struct/EnqueuedTaint edu/columbia/cs/psl/phosphor/struct/EnqueuedTaint edu/columbia/cs/psl/phosphor/struct/TaintedIntWithObjTag I edu/columbia/cs/psl/phosphor/runtime/Taint I edu/columbia/cs/psl/phosphor/runtime/Taint T I edu/columbia/cs/psl/phosphor/runtime/Taint edu/columbia/cs/psl/phosphor/runtime/Taint] []
    GETSTATIC java/lang/System.out : Ljava/io/PrintStream;
    ALOAD 11
    INVOKEVIRTUAL edu/columbia/cs/psl/phosphor/runtime/Taint.toString ()Ljava/lang/String;
    INVOKEVIRTUAL java/io/PrintStream.println (Ljava/lang/String;)V
   L23
    LINENUMBER 31 L23
    ALOAD 0
    ALOAD 1
    INVOKEVIRTUAL edu/columbia/cs/psl/phosphor/struct/ControlTaintTagStack.pop (Ledu/columbia/cs/psl/phosphor/struct/EnqueuedTaint;)V
    ALOAD 0
    ALOAD 2
    INVOKEVIRTUAL edu/columbia/cs/psl/phosphor/struct/ControlTaintTagStack.pop (Ledu/columbia/cs/psl/phosphor/struct/EnqueuedTaint;)V
    RETURN
   L24
    LOCALVARIABLE x I L7 L24 4
   L25
    LOCALVARIABLE phosphorShadowLV3 Ledu/columbia/cs/psl/phosphor/runtime/Taint; L11 L25 5
    LOCALVARIABLE phosphorReturnPreAlloc0 Ledu/columbia/cs/psl/phosphor/struct/TaintedIntWithObjTag; L3 L25 3
    LOCALVARIABLE phosphorJumpControlTag2 Ledu/columbia/cs/psl/phosphor/struct/EnqueuedTaint; L1 L25 2
    LOCALVARIABLE phosphorShadowLV4 Ledu/columbia/cs/psl/phosphor/runtime/Taint; L12 L25 7
    LOCALVARIABLE phosphorShadowLVFor6XX2 Ledu/columbia/cs/psl/phosphor/runtime/Taint; L9 L12 7
    LOCALVARIABLE phosphorJumpControlTag1 Ledu/columbia/cs/psl/phosphor/struct/EnqueuedTaint; L1 L25 1
    LOCALVARIABLE phosphorJumpControlTag0 Ledu/columbia/cs/psl/phosphor/struct/ControlTaintTagStack; L1 L25 0
    LOCALVARIABLE phosphorShadowLVFor4XX1 Ledu/columbia/cs/psl/phosphor/runtime/Taint; L6 L11 5
    LOCALVARIABLE phosphorShadowLV5 I L13 L14 8
    LOCALVARIABLE phosphorShadowLVFor9XX6 Ledu/columbia/cs/psl/phosphor/runtime/Taint; L15 L17 10
    LOCALVARIABLE phosphorShadowLV7 Ledu/columbia/cs/psl/phosphor/runtime/Taint; L17 L25 10
    LOCALVARIABLE y I L10 L24 6
    LOCALVARIABLE z I L16 L24 9
    LOCALVARIABLE tz Ledu/columbia/cs/psl/phosphor/runtime/Taint; L18 L24 11
    MAXSTACK = 104
    MAXLOCALS = 12

  // access flags 0x9
  public static testExample2()V
   L0
   L1
    NEW edu/columbia/cs/psl/phosphor/struct/ControlTaintTagStack
    DUP
    BIPUSH 2
    INVOKESPECIAL edu/columbia/cs/psl/phosphor/struct/ControlTaintTagStack.<init> (I)V
    ASTORE 0
    ACONST_NULL
    ASTORE 1
    ACONST_NULL
    ASTORE 2
   L2
   L3
   L4
    LINENUMBER 35 L4
    LDC "My string"
    ASTORE 3
   L5
    LINENUMBER 36 L5
    ALOAD 3
   L6
    NEW edu/columbia/cs/psl/phosphor/runtime/Taint
    DUP
    LDC "source x"
    INVOKESPECIAL edu/columbia/cs/psl/phosphor/runtime/Taint.<init> (Ljava/lang/Object;)V
    INVOKESTATIC edu/columbia/cs/psl/phosphor/runtime/MultiTainter.taintedObject (Ljava/lang/Object;Ledu/columbia/cs/psl/phosphor/runtime/Taint;)V
   L7
    LINENUMBER 37 L7
    ALOAD 3
    INVOKESTATIC com/josecambronero/ObjectTagExamples.identity (Ljava/lang/Object;)Ljava/lang/Object;
    ASTORE 4
   L8
    LINENUMBER 38 L8
    ALOAD 4
    INVOKESTATIC edu/columbia/cs/psl/phosphor/runtime/MultiTainter.getTaint (Ljava/lang/Object;)Ledu/columbia/cs/psl/phosphor/runtime/Taint;
    ASTORE 5
   L9
    LINENUMBER 39 L9
    GETSTATIC com/josecambronero/ObjectTagExamples.$assertionsDisabledPHOSPHOR_TAG : Ledu/columbia/cs/psl/phosphor/runtime/Taint;
    GETSTATIC com/josecambronero/ObjectTagExamples.$assertionsDisabled : Z
    DUP
    INVOKESTATIC edu/ucdavis/cs/cyberlab/BBPhosphor/util/TaintHelper.saveTaint (Ljava/lang/Object;)V
    LDC "hello i coupied this! branching counting 1"
    INVOKESTATIC edu/ucdavis/cs/cyberlab/BBPhosphor/util/TaintHelper.printx (Ljava/lang/String;)V
    SWAP
    ALOAD 0
    SWAP
    ALOAD 1
    INVOKEVIRTUAL edu/columbia/cs/psl/phosphor/struct/ControlTaintTagStack.push (Ledu/columbia/cs/psl/phosphor/runtime/Taint;Ledu/columbia/cs/psl/phosphor/struct/EnqueuedTaint;)Ledu/columbia/cs/psl/phosphor/struct/EnqueuedTaint;
    ASTORE 1
    IFNE L10
   L11
    ALOAD 5
    IFNONNULL L10
   L12
   L13
    NEW java/lang/AssertionError
    DUP
    INVOKESPECIAL java/lang/AssertionError.<init> ()V
    DUP
    ALOAD 0
    INVOKESTATIC edu/columbia/cs/psl/phosphor/runtime/Taint.combineTagsOnObject (Ljava/lang/Object;Ledu/columbia/cs/psl/phosphor/struct/ControlTaintTagStack;)V
    ALOAD 0
    ALOAD 2
    INVOKEVIRTUAL edu/columbia/cs/psl/phosphor/struct/ControlTaintTagStack.pop (Ledu/columbia/cs/psl/phosphor/struct/EnqueuedTaint;)V
    ALOAD 0
    ALOAD 1
    INVOKEVIRTUAL edu/columbia/cs/psl/phosphor/struct/ControlTaintTagStack.pop (Ledu/columbia/cs/psl/phosphor/struct/EnqueuedTaint;)V
    ATHROW
   L10
    LINENUMBER 40 L10
   FRAME FULL [edu/columbia/cs/psl/phosphor/struct/ControlTaintTagStack edu/columbia/cs/psl/phosphor/struct/EnqueuedTaint edu/columbia/cs/psl/phosphor/struct/EnqueuedTaint java/lang/Object java/lang/Object edu/columbia/cs/psl/phosphor/runtime/Taint] []
    GETSTATIC java/lang/System.out : Ljava/io/PrintStream;
    ALOAD 5
    INVOKEVIRTUAL edu/columbia/cs/psl/phosphor/runtime/Taint.getLabel ()Ljava/lang/Object;
    CHECKCAST java/lang/String
    INVOKEVIRTUAL java/io/PrintStream.println (Ljava/lang/String;)V
   L14
    LINENUMBER 41 L14
    GETSTATIC java/lang/System.out : Ljava/io/PrintStream;
    ALOAD 5
    INVOKEVIRTUAL edu/columbia/cs/psl/phosphor/runtime/Taint.toString ()Ljava/lang/String;
    INVOKEVIRTUAL java/io/PrintStream.println (Ljava/lang/String;)V
   L15
    LINENUMBER 42 L15
    ALOAD 0
    ALOAD 2
    INVOKEVIRTUAL edu/columbia/cs/psl/phosphor/struct/ControlTaintTagStack.pop (Ledu/columbia/cs/psl/phosphor/struct/EnqueuedTaint;)V
    ALOAD 0
    ALOAD 1
    INVOKEVIRTUAL edu/columbia/cs/psl/phosphor/struct/ControlTaintTagStack.pop (Ledu/columbia/cs/psl/phosphor/struct/EnqueuedTaint;)V
    RETURN
   L16
    LOCALVARIABLE s Ljava/lang/Object; L5 L16 3
   L17
    LOCALVARIABLE phosphorJumpControlTag0 Ledu/columbia/cs/psl/phosphor/struct/ControlTaintTagStack; L1 L17 0
    LOCALVARIABLE phosphorJumpControlTag2 Ledu/columbia/cs/psl/phosphor/struct/EnqueuedTaint; L1 L17 2
    LOCALVARIABLE phosphorJumpControlTag1 Ledu/columbia/cs/psl/phosphor/struct/EnqueuedTaint; L1 L17 1
    LOCALVARIABLE s2 Ljava/lang/Object; L8 L16 4
    LOCALVARIABLE tag Ledu/columbia/cs/psl/phosphor/runtime/Taint; L9 L16 5
    MAXSTACK = 104
    MAXLOCALS = 6

  // access flags 0x9
  public static testExample3()V
   L0
   L1
    NEW edu/columbia/cs/psl/phosphor/struct/ControlTaintTagStack
    DUP
    BIPUSH 6
    INVOKESPECIAL edu/columbia/cs/psl/phosphor/struct/ControlTaintTagStack.<init> (I)V
    ASTORE 0
    ACONST_NULL
    ASTORE 1
    ACONST_NULL
    ASTORE 2
    ACONST_NULL
    ASTORE 3
    ACONST_NULL
    ASTORE 4
    ACONST_NULL
    ASTORE 5
    ACONST_NULL
    ASTORE 6
   L2
   L3
    NEW edu/columbia/cs/psl/phosphor/struct/TaintedDoubleWithObjTag
    DUP
    INVOKESPECIAL edu/columbia/cs/psl/phosphor/struct/TaintedDoubleWithObjTag.<init> ()V
    ASTORE 7
   L4
   L5
    LINENUMBER 47 L5
    BIPUSH 33
    NEWARRAY T_DOUBLE
    DUP
   L6
    NEW edu/columbia/cs/psl/phosphor/struct/LazyDoubleArrayObjTags
    DUP_X1
    SWAP
    INVOKESPECIAL edu/columbia/cs/psl/phosphor/struct/LazyDoubleArrayObjTags.<init> ([D)V
    SWAP
    DUP
    ALOAD 0
    INVOKESTATIC edu/columbia/cs/psl/phosphor/runtime/Taint.combineTagsOnObject (Ljava/lang/Object;Ledu/columbia/cs/psl/phosphor/struct/ControlTaintTagStack;)V
   L7
    ASTORE 8
    ASTORE 9
   L8
    LINENUMBER 48 L8
    ALOAD 0
    INVOKEVIRTUAL edu/columbia/cs/psl/phosphor/struct/ControlTaintTagStack.copyTag ()Ledu/columbia/cs/psl/phosphor/runtime/Taint;
    ICONST_0
    SWAP
    ALOAD 0
    INVOKESTATIC edu/columbia/cs/psl/phosphor/runtime/Taint.combineTags (Ledu/columbia/cs/psl/phosphor/runtime/Taint;Ledu/columbia/cs/psl/phosphor/struct/ControlTaintTagStack;)Ledu/columbia/cs/psl/phosphor/runtime/Taint;
    SWAP
   L9
    ISTORE 10
    INVOKESTATIC edu/columbia/cs/psl/phosphor/runtime/Taint.copyTaint (Ledu/columbia/cs/psl/phosphor/runtime/Taint;)Ledu/columbia/cs/psl/phosphor/runtime/Taint;
    ASTORE 11
   L10
   FRAME FULL [edu/columbia/cs/psl/phosphor/struct/ControlTaintTagStack edu/columbia/cs/psl/phosphor/struct/EnqueuedTaint edu/columbia/cs/psl/phosphor/struct/EnqueuedTaint edu/columbia/cs/psl/phosphor/struct/EnqueuedTaint edu/columbia/cs/psl/phosphor/struct/EnqueuedTaint edu/columbia/cs/psl/phosphor/struct/EnqueuedTaint edu/columbia/cs/psl/phosphor/struct/EnqueuedTaint edu/columbia/cs/psl/phosphor/struct/TaintedDoubleWithObjTag [D edu/columbia/cs/psl/phosphor/struct/LazyDoubleArrayObjTags I edu/columbia/cs/psl/phosphor/runtime/Taint] []
   L11
    ALOAD 11
    ILOAD 10
    ALOAD 9
    ALOAD 8
    SWAP
    POP
    ACONST_NULL
    CHECKCAST edu/columbia/cs/psl/phosphor/runtime/Taint
    SWAP
    ARRAYLENGTH
   L12
    SWAP
    ASTORE 12
    DUP2_X1
    POP2
    ALOAD 0
    SWAP
    ALOAD 0
    ALOAD 12
   L13
    ALOAD 1
    INVOKEVIRTUAL edu/columbia/cs/psl/phosphor/struct/ControlTaintTagStack.push (Ledu/columbia/cs/psl/phosphor/runtime/Taint;Ledu/columbia/cs/psl/phosphor/struct/EnqueuedTaint;)Ledu/columbia/cs/psl/phosphor/struct/EnqueuedTaint;
    ASTORE 1
    ALOAD 2
    INVOKEVIRTUAL edu/columbia/cs/psl/phosphor/struct/ControlTaintTagStack.push (Ledu/columbia/cs/psl/phosphor/runtime/Taint;Ledu/columbia/cs/psl/phosphor/struct/EnqueuedTaint;)Ledu/columbia/cs/psl/phosphor/struct/EnqueuedTaint;
    ASTORE 2
    IF_ICMPGE L14
   L15
   L16
    LINENUMBER 49 L16
    ALOAD 9
    ALOAD 8
    ILOAD 10
   L17
    ALOAD 11
    ILOAD 10
    I2F
    F2D
   L18
    NEW java/lang/StringBuilder
    DUP
    INVOKESPECIAL java/lang/StringBuilder.<init> ()V
    LDC "Source "
    INVOKEVIRTUAL java/lang/StringBuilder.append (Ljava/lang/String;)Ljava/lang/StringBuilder;
   L19
    ALOAD 11
    ILOAD 10
    INVOKEVIRTUAL java/lang/StringBuilder.append$$PHOSPHORTAGGED (Ledu/columbia/cs/psl/phosphor/runtime/Taint;I)Ljava/lang/StringBuilder;
    INVOKEVIRTUAL java/lang/StringBuilder.toString ()Ljava/lang/String;
    ALOAD 7
    INVOKESTATIC edu/columbia/cs/psl/phosphor/runtime/MultiTainter.taintedDouble$$PHOSPHORTAGGED (Ledu/columbia/cs/psl/phosphor/runtime/Taint;DLjava/lang/Object;Ledu/columbia/cs/psl/phosphor/struct/TaintedDoubleWithObjTag;)Ledu/columbia/cs/psl/phosphor/struct/TaintedDoubleWithObjTag;
    DUP
    GETFIELD edu/columbia/cs/psl/phosphor/struct/TaintedDoubleWithObjTag.taint : Ledu/columbia/cs/psl/phosphor/runtime/Taint;
    SWAP
    GETFIELD edu/columbia/cs/psl/phosphor/struct/TaintedDoubleWithObjTag.val : D
    ALOAD 0
    INVOKEVIRTUAL edu/columbia/cs/psl/phosphor/struct/LazyDoubleArrayObjTags.setImplicit ([DILedu/columbia/cs/psl/phosphor/runtime/Taint;DLedu/columbia/cs/psl/phosphor/struct/ControlTaintTagStack;)V
   L20
    LINENUMBER 48 L20
    ALOAD 11
    ALOAD 0
    INVOKESTATIC edu/columbia/cs/psl/phosphor/runtime/Taint.combineTags (Ledu/columbia/cs/psl/phosphor/runtime/Taint;Ledu/columbia/cs/psl/phosphor/struct/ControlTaintTagStack;)Ledu/columbia/cs/psl/phosphor/runtime/Taint;
    ASTORE 11
    IINC 10 1
    GOTO L10
   L21
   L14
    LINENUMBER 52 L14
   FRAME FULL [edu/columbia/cs/psl/phosphor/struct/ControlTaintTagStack edu/columbia/cs/psl/phosphor/struct/EnqueuedTaint edu/columbia/cs/psl/phosphor/struct/EnqueuedTaint edu/columbia/cs/psl/phosphor/struct/EnqueuedTaint edu/columbia/cs/psl/phosphor/struct/EnqueuedTaint edu/columbia/cs/psl/phosphor/struct/EnqueuedTaint edu/columbia/cs/psl/phosphor/struct/EnqueuedTaint edu/columbia/cs/psl/phosphor/struct/TaintedDoubleWithObjTag [D edu/columbia/cs/psl/phosphor/struct/LazyDoubleArrayObjTags] []
    ALOAD 0
    INVOKEVIRTUAL edu/columbia/cs/psl/phosphor/struct/ControlTaintTagStack.copyTag ()Ledu/columbia/cs/psl/phosphor/runtime/Taint;
    DCONST_0
    DUP2_X1
    POP2
    ALOAD 0
    INVOKESTATIC edu/columbia/cs/psl/phosphor/runtime/Taint.combineTags (Ledu/columbia/cs/psl/phosphor/runtime/Taint;Ledu/columbia/cs/psl/phosphor/struct/ControlTaintTagStack;)Ledu/columbia/cs/psl/phosphor/runtime/Taint;
    DUP_X2
    POP
   L22
    DSTORE 13
    INVOKESTATIC edu/columbia/cs/psl/phosphor/runtime/Taint.copyTaint (Ledu/columbia/cs/psl/phosphor/runtime/Taint;)Ledu/columbia/cs/psl/phosphor/runtime/Taint;
    ASTORE 15
   L23
    LINENUMBER 53 L23
    ALOAD 9
    ALOAD 8
    DUP
    ALOAD 0
    INVOKESTATIC edu/columbia/cs/psl/phosphor/runtime/Taint.combineTagsOnObject (Ljava/lang/Object;Ledu/columbia/cs/psl/phosphor/struct/ControlTaintTagStack;)V
   L24
    ASTORE 16
    ASTORE 17
    ALOAD 17
    ALOAD 16
    SWAP
    POP
    ACONST_NULL
    CHECKCAST edu/columbia/cs/psl/phosphor/runtime/Taint
    SWAP
    ARRAYLENGTH
    SWAP
    ALOAD 0
    INVOKESTATIC edu/columbia/cs/psl/phosphor/runtime/Taint.combineTags (Ledu/columbia/cs/psl/phosphor/runtime/Taint;Ledu/columbia/cs/psl/phosphor/struct/ControlTaintTagStack;)Ledu/columbia/cs/psl/phosphor/runtime/Taint;
    SWAP
   L25
    ISTORE 18
    INVOKESTATIC edu/columbia/cs/psl/phosphor/runtime/Taint.copyTaint (Ledu/columbia/cs/psl/phosphor/runtime/Taint;)Ledu/columbia/cs/psl/phosphor/runtime/Taint;
    ASTORE 19
    ALOAD 0
    INVOKEVIRTUAL edu/columbia/cs/psl/phosphor/struct/ControlTaintTagStack.copyTag ()Ledu/columbia/cs/psl/phosphor/runtime/Taint;
    ICONST_0
    SWAP
    ALOAD 0
    INVOKESTATIC edu/columbia/cs/psl/phosphor/runtime/Taint.combineTags (Ledu/columbia/cs/psl/phosphor/runtime/Taint;Ledu/columbia/cs/psl/phosphor/struct/ControlTaintTagStack;)Ledu/columbia/cs/psl/phosphor/runtime/Taint;
    SWAP
   L26
    ISTORE 20
    INVOKESTATIC edu/columbia/cs/psl/phosphor/runtime/Taint.copyTaint (Ledu/columbia/cs/psl/phosphor/runtime/Taint;)Ledu/columbia/cs/psl/phosphor/runtime/Taint;
    ASTORE 21
   L27
   FRAME FULL [edu/columbia/cs/psl/phosphor/struct/ControlTaintTagStack edu/columbia/cs/psl/phosphor/struct/EnqueuedTaint edu/columbia/cs/psl/phosphor/struct/EnqueuedTaint edu/columbia/cs/psl/phosphor/struct/EnqueuedTaint edu/columbia/cs/psl/phosphor/struct/EnqueuedTaint edu/columbia/cs/psl/phosphor/struct/EnqueuedTaint edu/columbia/cs/psl/phosphor/struct/EnqueuedTaint edu/columbia/cs/psl/phosphor/struct/TaintedDoubleWithObjTag [D edu/columbia/cs/psl/phosphor/struct/LazyDoubleArrayObjTags T T T D edu/columbia/cs/psl/phosphor/runtime/Taint [D edu/columbia/cs/psl/phosphor/struct/LazyDoubleArrayObjTags I edu/columbia/cs/psl/phosphor/runtime/Taint I edu/columbia/cs/psl/phosphor/runtime/Taint] []
   L28
    ALOAD 21
    ILOAD 20
   L29
    ALOAD 19
    ILOAD 18
    SWAP
    ASTORE 12
    DUP2_X1
    POP2
    ALOAD 0
    SWAP
    ALOAD 0
    ALOAD 12
   L30
    ALOAD 3
    INVOKEVIRTUAL edu/columbia/cs/psl/phosphor/struct/ControlTaintTagStack.push (Ledu/columbia/cs/psl/phosphor/runtime/Taint;Ledu/columbia/cs/psl/phosphor/struct/EnqueuedTaint;)Ledu/columbia/cs/psl/phosphor/struct/EnqueuedTaint;
    ASTORE 3
    ALOAD 4
    INVOKEVIRTUAL edu/columbia/cs/psl/phosphor/struct/ControlTaintTagStack.push (Ledu/columbia/cs/psl/phosphor/runtime/Taint;Ledu/columbia/cs/psl/phosphor/struct/EnqueuedTaint;)Ledu/columbia/cs/psl/phosphor/struct/EnqueuedTaint;
    ASTORE 4
    IF_ICMPGE L31
   L32
    ALOAD 17
    ALOAD 16
    ILOAD 20
    ALOAD 7
    ALOAD 0
    INVOKEVIRTUAL edu/columbia/cs/psl/phosphor/struct/LazyDoubleArrayObjTags.getImplicit ([DILedu/columbia/cs/psl/phosphor/struct/TaintedDoubleWithObjTag;Ledu/columbia/cs/psl/phosphor/struct/ControlTaintTagStack;)Ledu/columbia/cs/psl/phosphor/struct/TaintedDoubleWithObjTag;
    DUP
    GETFIELD edu/columbia/cs/psl/phosphor/struct/TaintedDoubleWithObjTag.taint : Ledu/columbia/cs/psl/phosphor/runtime/Taint;
    SWAP
    GETFIELD edu/columbia/cs/psl/phosphor/struct/TaintedDoubleWithObjTag.val : D
    DUP2_X1
    POP2
    ALOAD 0
    INVOKESTATIC edu/columbia/cs/psl/phosphor/runtime/Taint.combineTags (Ledu/columbia/cs/psl/phosphor/runtime/Taint;Ledu/columbia/cs/psl/phosphor/struct/ControlTaintTagStack;)Ledu/columbia/cs/psl/phosphor/runtime/Taint;
    DUP_X2
    POP
   L33
    DSTORE 22
    INVOKESTATIC edu/columbia/cs/psl/phosphor/runtime/Taint.copyTaint (Ledu/columbia/cs/psl/phosphor/runtime/Taint;)Ledu/columbia/cs/psl/phosphor/runtime/Taint;
    ASTORE 24
   L34
    LINENUMBER 54 L34
   L35
    ALOAD 15
    DLOAD 13
   L36
    ALOAD 24
    DLOAD 22
   L37
    DSTORE 25
    DUP_X2
    POP
   L38
    DSTORE 27
    INVOKESTATIC edu/columbia/cs/psl/phosphor/runtime/Taint.combineTags (Ledu/columbia/cs/psl/phosphor/runtime/Taint;Ledu/columbia/cs/psl/phosphor/runtime/Taint;)Ledu/columbia/cs/psl/phosphor/runtime/Taint;
    DLOAD 27
    DLOAD 25
    DADD
   L39
   L40
    DUP2_X1
    POP2
    ALOAD 0
    INVOKESTATIC edu/columbia/cs/psl/phosphor/runtime/Taint.combineTags (Ledu/columbia/cs/psl/phosphor/runtime/Taint;Ledu/columbia/cs/psl/phosphor/struct/ControlTaintTagStack;)Ledu/columbia/cs/psl/phosphor/runtime/Taint;
    DUP_X2
    POP
   L41
    DSTORE 13
    INVOKESTATIC edu/columbia/cs/psl/phosphor/runtime/Taint.copyTaint (Ledu/columbia/cs/psl/phosphor/runtime/Taint;)Ledu/columbia/cs/psl/phosphor/runtime/Taint;
    ASTORE 15
   L42
    LINENUMBER 53 L42
    ALOAD 21
    ALOAD 0
    INVOKESTATIC edu/columbia/cs/psl/phosphor/runtime/Taint.combineTags (Ledu/columbia/cs/psl/phosphor/runtime/Taint;Ledu/columbia/cs/psl/phosphor/struct/ControlTaintTagStack;)Ledu/columbia/cs/psl/phosphor/runtime/Taint;
    ASTORE 21
    IINC 20 1
    GOTO L27
   L43
   L31
    LINENUMBER 56 L31
   FRAME FULL [edu/columbia/cs/psl/phosphor/struct/ControlTaintTagStack edu/columbia/cs/psl/phosphor/struct/EnqueuedTaint edu/columbia/cs/psl/phosphor/struct/EnqueuedTaint edu/columbia/cs/psl/phosphor/struct/EnqueuedTaint edu/columbia/cs/psl/phosphor/struct/EnqueuedTaint edu/columbia/cs/psl/phosphor/struct/EnqueuedTaint edu/columbia/cs/psl/phosphor/struct/EnqueuedTaint edu/columbia/cs/psl/phosphor/struct/TaintedDoubleWithObjTag [D edu/columbia/cs/psl/phosphor/struct/LazyDoubleArrayObjTags T T T D edu/columbia/cs/psl/phosphor/runtime/Taint] []
    ALOAD 15
    DLOAD 13
    INVOKESTATIC edu/columbia/cs/psl/phosphor/runtime/MultiTainter.getTaint$$PHOSPHORTAGGED (Ledu/columbia/cs/psl/phosphor/runtime/Taint;D)Ledu/columbia/cs/psl/phosphor/runtime/Taint;
    ASTORE 16
   L44
    LINENUMBER 57 L44
    GETSTATIC com/josecambronero/ObjectTagExamples.$assertionsDisabledPHOSPHOR_TAG : Ledu/columbia/cs/psl/phosphor/runtime/Taint;
    GETSTATIC com/josecambronero/ObjectTagExamples.$assertionsDisabled : Z
    DUP
    INVOKESTATIC edu/ucdavis/cs/cyberlab/BBPhosphor/util/TaintHelper.saveTaint (Ljava/lang/Object;)V
    LDC "hello i coupied this! branching counting 5"
    INVOKESTATIC edu/ucdavis/cs/cyberlab/BBPhosphor/util/TaintHelper.printx (Ljava/lang/String;)V
    SWAP
    ALOAD 0
    SWAP
    ALOAD 5
    INVOKEVIRTUAL edu/columbia/cs/psl/phosphor/struct/ControlTaintTagStack.push (Ledu/columbia/cs/psl/phosphor/runtime/Taint;Ledu/columbia/cs/psl/phosphor/struct/EnqueuedTaint;)Ledu/columbia/cs/psl/phosphor/struct/EnqueuedTaint;
    ASTORE 5
    IFNE L45
   L46
    ALOAD 16
    IFNONNULL L45
   L47
   L48
    NEW java/lang/AssertionError
    DUP
    INVOKESPECIAL java/lang/AssertionError.<init> ()V
    DUP
    ALOAD 0
    INVOKESTATIC edu/columbia/cs/psl/phosphor/runtime/Taint.combineTagsOnObject (Ljava/lang/Object;Ledu/columbia/cs/psl/phosphor/struct/ControlTaintTagStack;)V
    ALOAD 0
    ALOAD 6
    INVOKEVIRTUAL edu/columbia/cs/psl/phosphor/struct/ControlTaintTagStack.pop (Ledu/columbia/cs/psl/phosphor/struct/EnqueuedTaint;)V
    ALOAD 0
    ALOAD 5
    INVOKEVIRTUAL edu/columbia/cs/psl/phosphor/struct/ControlTaintTagStack.pop (Ledu/columbia/cs/psl/phosphor/struct/EnqueuedTaint;)V
    ALOAD 0
    ALOAD 3
    INVOKEVIRTUAL edu/columbia/cs/psl/phosphor/struct/ControlTaintTagStack.pop (Ledu/columbia/cs/psl/phosphor/struct/EnqueuedTaint;)V
    ALOAD 0
    ALOAD 4
    INVOKEVIRTUAL edu/columbia/cs/psl/phosphor/struct/ControlTaintTagStack.pop (Ledu/columbia/cs/psl/phosphor/struct/EnqueuedTaint;)V
    ALOAD 0
    ALOAD 1
    INVOKEVIRTUAL edu/columbia/cs/psl/phosphor/struct/ControlTaintTagStack.pop (Ledu/columbia/cs/psl/phosphor/struct/EnqueuedTaint;)V
    ALOAD 0
    ALOAD 2
    INVOKEVIRTUAL edu/columbia/cs/psl/phosphor/struct/ControlTaintTagStack.pop (Ledu/columbia/cs/psl/phosphor/struct/EnqueuedTaint;)V
    ATHROW
   L45
    LINENUMBER 58 L45
   FRAME FULL [edu/columbia/cs/psl/phosphor/struct/ControlTaintTagStack edu/columbia/cs/psl/phosphor/struct/EnqueuedTaint edu/columbia/cs/psl/phosphor/struct/EnqueuedTaint edu/columbia/cs/psl/phosphor/struct/EnqueuedTaint edu/columbia/cs/psl/phosphor/struct/EnqueuedTaint edu/columbia/cs/psl/phosphor/struct/EnqueuedTaint edu/columbia/cs/psl/phosphor/struct/EnqueuedTaint edu/columbia/cs/psl/phosphor/struct/TaintedDoubleWithObjTag [D edu/columbia/cs/psl/phosphor/struct/LazyDoubleArrayObjTags T T T D edu/columbia/cs/psl/phosphor/runtime/Taint edu/columbia/cs/psl/phosphor/runtime/Taint] []
    GETSTATIC java/lang/System.out : Ljava/io/PrintStream;
    ALOAD 16
    INVOKEVIRTUAL edu/columbia/cs/psl/phosphor/runtime/Taint.toString ()Ljava/lang/String;
    INVOKEVIRTUAL java/io/PrintStream.println (Ljava/lang/String;)V
   L49
    LINENUMBER 59 L49
    ALOAD 0
    ALOAD 6
    INVOKEVIRTUAL edu/columbia/cs/psl/phosphor/struct/ControlTaintTagStack.pop (Ledu/columbia/cs/psl/phosphor/struct/EnqueuedTaint;)V
    ALOAD 0
    ALOAD 5
    INVOKEVIRTUAL edu/columbia/cs/psl/phosphor/struct/ControlTaintTagStack.pop (Ledu/columbia/cs/psl/phosphor/struct/EnqueuedTaint;)V
    ALOAD 0
    ALOAD 3
    INVOKEVIRTUAL edu/columbia/cs/psl/phosphor/struct/ControlTaintTagStack.pop (Ledu/columbia/cs/psl/phosphor/struct/EnqueuedTaint;)V
    ALOAD 0
    ALOAD 4
    INVOKEVIRTUAL edu/columbia/cs/psl/phosphor/struct/ControlTaintTagStack.pop (Ledu/columbia/cs/psl/phosphor/struct/EnqueuedTaint;)V
    ALOAD 0
    ALOAD 1
    INVOKEVIRTUAL edu/columbia/cs/psl/phosphor/struct/ControlTaintTagStack.pop (Ledu/columbia/cs/psl/phosphor/struct/EnqueuedTaint;)V
    ALOAD 0
    ALOAD 2
    INVOKEVIRTUAL edu/columbia/cs/psl/phosphor/struct/ControlTaintTagStack.pop (Ledu/columbia/cs/psl/phosphor/struct/EnqueuedTaint;)V
    RETURN
   L50
    LOCALVARIABLE i I L10 L14 10
   L51
    LOCALVARIABLE phosphorReturnPreAlloc0 Ledu/columbia/cs/psl/phosphor/struct/TaintedDoubleWithObjTag; L3 L51 7
    LOCALVARIABLE phosphorShadowLVFor20XX10 Ledu/columbia/cs/psl/phosphor/runtime/Taint; L26 L28 21
    LOCALVARIABLE phosphorShadowLV17 D L38 L39 27
    LOCALVARIABLE phosphorShadowLV11 Ledu/columbia/cs/psl/phosphor/runtime/Taint; L28 L51 21
    LOCALVARIABLE phosphorJumpControlTag1 Ledu/columbia/cs/psl/phosphor/struct/EnqueuedTaint; L1 L51 1
    LOCALVARIABLE phosphorShadowLVFor8XX1 Ledu/columbia/cs/psl/phosphor/struct/LazyDoubleArrayObjTags; L7 L51 9
    LOCALVARIABLE phosphorShadowLV3 Ledu/columbia/cs/psl/phosphor/runtime/Taint; L11 L17 11
    LOCALVARIABLE phosphorShadowLV12 Ledu/columbia/cs/psl/phosphor/runtime/Taint; L29 L51 19
    LOCALVARIABLE phosphorShadowLV18 Ledu/columbia/cs/psl/phosphor/runtime/Taint; L41 L51 15
    LOCALVARIABLE phosphorShadowLVFor18XX9 Ledu/columbia/cs/psl/phosphor/runtime/Taint; L25 L29 19
    LOCALVARIABLE phosphorShadowLV16 D L37 L40 25
    LOCALVARIABLE phosphorShadowLVFor16XX8 Ledu/columbia/cs/psl/phosphor/struct/LazyDoubleArrayObjTags; L24 L51 17
    LOCALVARIABLE phosphorJumpControlTag6 Ledu/columbia/cs/psl/phosphor/struct/EnqueuedTaint; L1 L51 6
    LOCALVARIABLE phosphorJumpControlTag2 Ledu/columbia/cs/psl/phosphor/struct/EnqueuedTaint; L1 L51 2
    LOCALVARIABLE phosphorShadowLVFor10XX2 Ledu/columbia/cs/psl/phosphor/runtime/Taint; L9 L11 11
    LOCALVARIABLE phosphorJumpControlTag4 Ledu/columbia/cs/psl/phosphor/struct/EnqueuedTaint; L1 L51 4
    LOCALVARIABLE phosphorShadowLVFor22XX13 Ledu/columbia/cs/psl/phosphor/runtime/Taint; L33 L36 24
    LOCALVARIABLE phosphorJumpControlTag3 Ledu/columbia/cs/psl/phosphor/struct/EnqueuedTaint; L1 L51 3
    LOCALVARIABLE phosphorShadowLV6 Ledu/columbia/cs/psl/phosphor/runtime/Taint; L19 L51 11
    LOCALVARIABLE phosphorShadowLV14 Ledu/columbia/cs/psl/phosphor/runtime/Taint; L35 L41 15
    LOCALVARIABLE phosphorJumpControlTag5 Ledu/columbia/cs/psl/phosphor/struct/EnqueuedTaint; L1 L51 5
    LOCALVARIABLE phosphorJumpControlTag0 Ledu/columbia/cs/psl/phosphor/struct/ControlTaintTagStack; L1 L51 0
    LOCALVARIABLE phosphorShadowLV5 Ledu/columbia/cs/psl/phosphor/runtime/Taint; L17 L19 11
    LOCALVARIABLE phosphorShadowLV15 Ledu/columbia/cs/psl/phosphor/runtime/Taint; L36 L51 24
    LOCALVARIABLE phosphorShadowLVFor13XX7 Ledu/columbia/cs/psl/phosphor/runtime/Taint; L22 L35 15
    LOCALVARIABLE phosphorShadowLV4 I L12 L30 12
    LOCALVARIABLE elem D L34 L42 22
    LOCALVARIABLE mydata [D L8 L50 8
    LOCALVARIABLE result D L23 L50 13
    LOCALVARIABLE tag Ledu/columbia/cs/psl/phosphor/runtime/Taint; L44 L50 16
    MAXSTACK = 106
    MAXLOCALS = 29

  // access flags 0x9
  public static testExample4()V
   L0
   L1
    NEW edu/columbia/cs/psl/phosphor/struct/ControlTaintTagStack
    DUP
    BIPUSH 3
    INVOKESPECIAL edu/columbia/cs/psl/phosphor/struct/ControlTaintTagStack.<init> (I)V
    ASTORE 0
    ACONST_NULL
    ASTORE 1
    ACONST_NULL
    ASTORE 2
    ACONST_NULL
    ASTORE 3
   L2
   L3
    NEW edu/columbia/cs/psl/phosphor/struct/TaintedDoubleWithObjTag
    DUP
    INVOKESPECIAL edu/columbia/cs/psl/phosphor/struct/TaintedDoubleWithObjTag.<init> ()V
    ASTORE 4
   L4
    NEW edu/columbia/cs/psl/phosphor/struct/TaintedIntWithObjTag
    DUP
    INVOKESPECIAL edu/columbia/cs/psl/phosphor/struct/TaintedIntWithObjTag.<init> ()V
    ASTORE 5
   L5
   L6
    LINENUMBER 63 L6
    ALOAD 0
    INVOKEVIRTUAL edu/columbia/cs/psl/phosphor/struct/ControlTaintTagStack.copyTag ()Ledu/columbia/cs/psl/phosphor/runtime/Taint;
    BIPUSH 100
    LDC "x"
    ALOAD 5
    INVOKESTATIC edu/columbia/cs/psl/phosphor/runtime/MultiTainter.taintedInt$$PHOSPHORTAGGED (Ledu/columbia/cs/psl/phosphor/runtime/Taint;ILjava/lang/Object;Ledu/columbia/cs/psl/phosphor/struct/TaintedIntWithObjTag;)Ledu/columbia/cs/psl/phosphor/struct/TaintedIntWithObjTag;
    DUP
    GETFIELD edu/columbia/cs/psl/phosphor/struct/TaintedIntWithObjTag.taint : Ledu/columbia/cs/psl/phosphor/runtime/Taint;
    SWAP
    GETFIELD edu/columbia/cs/psl/phosphor/struct/TaintedIntWithObjTag.val : I
    SWAP
    ALOAD 0
    INVOKESTATIC edu/columbia/cs/psl/phosphor/runtime/Taint.combineTags (Ledu/columbia/cs/psl/phosphor/runtime/Taint;Ledu/columbia/cs/psl/phosphor/struct/ControlTaintTagStack;)Ledu/columbia/cs/psl/phosphor/runtime/Taint;
    SWAP
   L7
    ISTORE 6
    INVOKESTATIC edu/columbia/cs/psl/phosphor/runtime/Taint.copyTaint (Ledu/columbia/cs/psl/phosphor/runtime/Taint;)Ledu/columbia/cs/psl/phosphor/runtime/Taint;
    ASTORE 7
   L8
    LINENUMBER 64 L8
    ALOAD 0
    INVOKEVIRTUAL edu/columbia/cs/psl/phosphor/struct/ControlTaintTagStack.copyTag ()Ledu/columbia/cs/psl/phosphor/runtime/Taint;
    BIPUSH 100
    LDC "y"
    ALOAD 5
    INVOKESTATIC edu/columbia/cs/psl/phosphor/runtime/MultiTainter.taintedInt$$PHOSPHORTAGGED (Ledu/columbia/cs/psl/phosphor/runtime/Taint;ILjava/lang/Object;Ledu/columbia/cs/psl/phosphor/struct/TaintedIntWithObjTag;)Ledu/columbia/cs/psl/phosphor/struct/TaintedIntWithObjTag;
    DUP
    GETFIELD edu/columbia/cs/psl/phosphor/struct/TaintedIntWithObjTag.taint : Ledu/columbia/cs/psl/phosphor/runtime/Taint;
    SWAP
    GETFIELD edu/columbia/cs/psl/phosphor/struct/TaintedIntWithObjTag.val : I
    SWAP
    ALOAD 0
    INVOKESTATIC edu/columbia/cs/psl/phosphor/runtime/Taint.combineTags (Ledu/columbia/cs/psl/phosphor/runtime/Taint;Ledu/columbia/cs/psl/phosphor/struct/ControlTaintTagStack;)Ledu/columbia/cs/psl/phosphor/runtime/Taint;
    SWAP
   L9
    ISTORE 8
    INVOKESTATIC edu/columbia/cs/psl/phosphor/runtime/Taint.copyTaint (Ledu/columbia/cs/psl/phosphor/runtime/Taint;)Ledu/columbia/cs/psl/phosphor/runtime/Taint;
    ASTORE 9
   L10
    LINENUMBER 65 L10
   L11
    ALOAD 7
    ILOAD 6
   L12
    ALOAD 9
    ILOAD 8
   L13
    ISTORE 10
    SWAP
    ILOAD 10
   L14
    IADD
    DUP_X2
    POP
    INVOKESTATIC edu/columbia/cs/psl/phosphor/runtime/Taint.combineTags (Ledu/columbia/cs/psl/phosphor/runtime/Taint;Ledu/columbia/cs/psl/phosphor/runtime/Taint;)Ledu/columbia/cs/psl/phosphor/runtime/Taint;
    SWAP
    SWAP
    ALOAD 0
    INVOKESTATIC edu/columbia/cs/psl/phosphor/runtime/Taint.combineTags (Ledu/columbia/cs/psl/phosphor/runtime/Taint;Ledu/columbia/cs/psl/phosphor/struct/ControlTaintTagStack;)Ledu/columbia/cs/psl/phosphor/runtime/Taint;
    SWAP
   L15
    ISTORE 11
    INVOKESTATIC edu/columbia/cs/psl/phosphor/runtime/Taint.copyTaint (Ledu/columbia/cs/psl/phosphor/runtime/Taint;)Ledu/columbia/cs/psl/phosphor/runtime/Taint;
    ASTORE 12
   L16
    LINENUMBER 66 L16
    ALOAD 0
    INVOKEVIRTUAL edu/columbia/cs/psl/phosphor/struct/ControlTaintTagStack.copyTag ()Ledu/columbia/cs/psl/phosphor/runtime/Taint;
    LDC 100.0
    LDC "w"
    ALOAD 4
    INVOKESTATIC edu/columbia/cs/psl/phosphor/runtime/MultiTainter.taintedDouble$$PHOSPHORTAGGED (Ledu/columbia/cs/psl/phosphor/runtime/Taint;DLjava/lang/Object;Ledu/columbia/cs/psl/phosphor/struct/TaintedDoubleWithObjTag;)Ledu/columbia/cs/psl/phosphor/struct/TaintedDoubleWithObjTag;
    DUP
    GETFIELD edu/columbia/cs/psl/phosphor/struct/TaintedDoubleWithObjTag.taint : Ledu/columbia/cs/psl/phosphor/runtime/Taint;
    SWAP
    GETFIELD edu/columbia/cs/psl/phosphor/struct/TaintedDoubleWithObjTag.val : D
    DUP2_X1
    POP2
    ALOAD 0
    INVOKESTATIC edu/columbia/cs/psl/phosphor/runtime/Taint.combineTags (Ledu/columbia/cs/psl/phosphor/runtime/Taint;Ledu/columbia/cs/psl/phosphor/struct/ControlTaintTagStack;)Ledu/columbia/cs/psl/phosphor/runtime/Taint;
    DUP_X2
    POP
   L17
    DSTORE 13
    INVOKESTATIC edu/columbia/cs/psl/phosphor/runtime/Taint.copyTaint (Ledu/columbia/cs/psl/phosphor/runtime/Taint;)Ledu/columbia/cs/psl/phosphor/runtime/Taint;
    ASTORE 15
   L18
    LINENUMBER 67 L18
    ALOAD 0
    INVOKEVIRTUAL edu/columbia/cs/psl/phosphor/struct/ControlTaintTagStack.copyTag ()Ledu/columbia/cs/psl/phosphor/runtime/Taint;
    ICONST_0
    SWAP
    ALOAD 0
    INVOKESTATIC edu/columbia/cs/psl/phosphor/runtime/Taint.combineTags (Ledu/columbia/cs/psl/phosphor/runtime/Taint;Ledu/columbia/cs/psl/phosphor/struct/ControlTaintTagStack;)Ledu/columbia/cs/psl/phosphor/runtime/Taint;
    SWAP
   L19
    ISTORE 16
    INVOKESTATIC edu/columbia/cs/psl/phosphor/runtime/Taint.copyTaint (Ledu/columbia/cs/psl/phosphor/runtime/Taint;)Ledu/columbia/cs/psl/phosphor/runtime/Taint;
    ASTORE 17
   L20
    LINENUMBER 69 L20
   L21
    ALOAD 12
    ILOAD 11
   L22
    ALOAD 15
    DLOAD 13
    D2I
    ISTORE 10
    SWAP
    ILOAD 10
   L23
    IADD
    DUP_X2
    POP
    INVOKESTATIC edu/columbia/cs/psl/phosphor/runtime/Taint.combineTags (Ledu/columbia/cs/psl/phosphor/runtime/Taint;Ledu/columbia/cs/psl/phosphor/runtime/Taint;)Ledu/columbia/cs/psl/phosphor/runtime/Taint;
    SWAP
   L24
    ALOAD 17
    ILOAD 16
    ISTORE 10
    SWAP
    ILOAD 10
   L25
    IADD
    DUP_X2
    POP
    INVOKESTATIC edu/columbia/cs/psl/phosphor/runtime/Taint.combineTags (Ledu/columbia/cs/psl/phosphor/runtime/Taint;Ledu/columbia/cs/psl/phosphor/runtime/Taint;)Ledu/columbia/cs/psl/phosphor/runtime/Taint;
    SWAP
    SWAP
    ALOAD 0
    INVOKESTATIC edu/columbia/cs/psl/phosphor/runtime/Taint.combineTags (Ledu/columbia/cs/psl/phosphor/runtime/Taint;Ledu/columbia/cs/psl/phosphor/struct/ControlTaintTagStack;)Ledu/columbia/cs/psl/phosphor/runtime/Taint;
    SWAP
   L26
    ISTORE 18
    INVOKESTATIC edu/columbia/cs/psl/phosphor/runtime/Taint.copyTaint (Ledu/columbia/cs/psl/phosphor/runtime/Taint;)Ledu/columbia/cs/psl/phosphor/runtime/Taint;
    ASTORE 19
   L27
    LINENUMBER 70 L27
   L28
    ALOAD 19
    ILOAD 18
    INVOKESTATIC edu/columbia/cs/psl/phosphor/runtime/MultiTainter.getTaint$$PHOSPHORTAGGED (Ledu/columbia/cs/psl/phosphor/runtime/Taint;I)Ledu/columbia/cs/psl/phosphor/runtime/Taint;
    ASTORE 20
   L29
    LINENUMBER 71 L29
    GETSTATIC com/josecambronero/ObjectTagExamples.$assertionsDisabledPHOSPHOR_TAG : Ledu/columbia/cs/psl/phosphor/runtime/Taint;
    GETSTATIC com/josecambronero/ObjectTagExamples.$assertionsDisabled : Z
    DUP
    INVOKESTATIC edu/ucdavis/cs/cyberlab/BBPhosphor/util/TaintHelper.saveTaint (Ljava/lang/Object;)V
    LDC "hello i coupied this! branching counting 1"
    INVOKESTATIC edu/ucdavis/cs/cyberlab/BBPhosphor/util/TaintHelper.printx (Ljava/lang/String;)V
    SWAP
    ALOAD 0
    SWAP
    ALOAD 1
    INVOKEVIRTUAL edu/columbia/cs/psl/phosphor/struct/ControlTaintTagStack.push (Ledu/columbia/cs/psl/phosphor/runtime/Taint;Ledu/columbia/cs/psl/phosphor/struct/EnqueuedTaint;)Ledu/columbia/cs/psl/phosphor/struct/EnqueuedTaint;
    ASTORE 1
    IFNE L30
   L31
    ALOAD 20
    IFNONNULL L30
   L32
   L33
    NEW java/lang/AssertionError
    DUP
    INVOKESPECIAL java/lang/AssertionError.<init> ()V
    DUP
    ALOAD 0
    INVOKESTATIC edu/columbia/cs/psl/phosphor/runtime/Taint.combineTagsOnObject (Ljava/lang/Object;Ledu/columbia/cs/psl/phosphor/struct/ControlTaintTagStack;)V
    ALOAD 0
    ALOAD 2
    INVOKEVIRTUAL edu/columbia/cs/psl/phosphor/struct/ControlTaintTagStack.pop (Ledu/columbia/cs/psl/phosphor/struct/EnqueuedTaint;)V
    ALOAD 0
    ALOAD 1
    INVOKEVIRTUAL edu/columbia/cs/psl/phosphor/struct/ControlTaintTagStack.pop (Ledu/columbia/cs/psl/phosphor/struct/EnqueuedTaint;)V
    ATHROW
   L30
    LINENUMBER 72 L30
   FRAME FULL [edu/columbia/cs/psl/phosphor/struct/ControlTaintTagStack edu/columbia/cs/psl/phosphor/struct/EnqueuedTaint edu/columbia/cs/psl/phosphor/struct/EnqueuedTaint edu/columbia/cs/psl/phosphor/struct/EnqueuedTaint edu/columbia/cs/psl/phosphor/struct/TaintedDoubleWithObjTag edu/columbia/cs/psl/phosphor/struct/TaintedIntWithObjTag I edu/columbia/cs/psl/phosphor/runtime/Taint I edu/columbia/cs/psl/phosphor/runtime/Taint T I edu/columbia/cs/psl/phosphor/runtime/Taint D edu/columbia/cs/psl/phosphor/runtime/Taint I edu/columbia/cs/psl/phosphor/runtime/Taint I edu/columbia/cs/psl/phosphor/runtime/Taint edu/columbia/cs/psl/phosphor/runtime/Taint] []
    ALOAD 20
    INVOKEVIRTUAL edu/columbia/cs/psl/phosphor/runtime/Taint.getDependencies ()Ledu/columbia/cs/psl/phosphor/struct/LinkedList;
    ASTORE 21
   L34
    LINENUMBER 73 L34
    GETSTATIC java/lang/System.out : Ljava/io/PrintStream;
    ALOAD 21
    INVOKEVIRTUAL edu/columbia/cs/psl/phosphor/struct/LinkedList.toString ()Ljava/lang/String;
    INVOKEVIRTUAL java/io/PrintStream.println (Ljava/lang/String;)V
   L35
    LINENUMBER 76 L35
    ALOAD 21
    INVOKEVIRTUAL edu/columbia/cs/psl/phosphor/struct/LinkedList.getFirst ()Ledu/columbia/cs/psl/phosphor/struct/LinkedList$Node;
    ASTORE 22
   L36
    LINENUMBER 77 L36
   FRAME FULL [edu/columbia/cs/psl/phosphor/struct/ControlTaintTagStack edu/columbia/cs/psl/phosphor/struct/EnqueuedTaint edu/columbia/cs/psl/phosphor/struct/EnqueuedTaint edu/columbia/cs/psl/phosphor/struct/EnqueuedTaint edu/columbia/cs/psl/phosphor/struct/TaintedDoubleWithObjTag edu/columbia/cs/psl/phosphor/struct/TaintedIntWithObjTag I edu/columbia/cs/psl/phosphor/runtime/Taint I edu/columbia/cs/psl/phosphor/runtime/Taint T I edu/columbia/cs/psl/phosphor/runtime/Taint D edu/columbia/cs/psl/phosphor/runtime/Taint I edu/columbia/cs/psl/phosphor/runtime/Taint I edu/columbia/cs/psl/phosphor/runtime/Taint edu/columbia/cs/psl/phosphor/runtime/Taint edu/columbia/cs/psl/phosphor/struct/LinkedList edu/columbia/cs/psl/phosphor/struct/LinkedList$Node] []
    ALOAD 22
    IFNULL L37
   L38
   L39
    LINENUMBER 78 L39
    ALOAD 22
    GETFIELD edu/columbia/cs/psl/phosphor/struct/LinkedList$Node.entry : Ljava/lang/Object;
    CHECKCAST java/lang/String
    ASTORE 23
   L40
    LINENUMBER 79 L40
    GETSTATIC java/lang/System.out : Ljava/io/PrintStream;
    ALOAD 23
    INVOKEVIRTUAL java/io/PrintStream.println (Ljava/lang/String;)V
   L41
    LINENUMBER 80 L41
    ALOAD 22
    GETFIELD edu/columbia/cs/psl/phosphor/struct/LinkedList$Node.next : Ledu/columbia/cs/psl/phosphor/struct/LinkedList$Node;
    ASTORE 22
   L42
    LINENUMBER 81 L42
    GOTO L36
   L43
   L37
    LINENUMBER 82 L37
   FRAME FULL [edu/columbia/cs/psl/phosphor/struct/ControlTaintTagStack edu/columbia/cs/psl/phosphor/struct/EnqueuedTaint edu/columbia/cs/psl/phosphor/struct/EnqueuedTaint edu/columbia/cs/psl/phosphor/struct/EnqueuedTaint edu/columbia/cs/psl/phosphor/struct/TaintedDoubleWithObjTag edu/columbia/cs/psl/phosphor/struct/TaintedIntWithObjTag I edu/columbia/cs/psl/phosphor/runtime/Taint I edu/columbia/cs/psl/phosphor/runtime/Taint T I edu/columbia/cs/psl/phosphor/runtime/Taint D edu/columbia/cs/psl/phosphor/runtime/Taint I edu/columbia/cs/psl/phosphor/runtime/Taint I edu/columbia/cs/psl/phosphor/runtime/Taint edu/columbia/cs/psl/phosphor/runtime/Taint edu/columbia/cs/psl/phosphor/struct/LinkedList edu/columbia/cs/psl/phosphor/struct/LinkedList$Node] []
    ALOAD 0
    ALOAD 2
    INVOKEVIRTUAL edu/columbia/cs/psl/phosphor/struct/ControlTaintTagStack.pop (Ledu/columbia/cs/psl/phosphor/struct/EnqueuedTaint;)V
    ALOAD 0
    ALOAD 1
    INVOKEVIRTUAL edu/columbia/cs/psl/phosphor/struct/ControlTaintTagStack.pop (Ledu/columbia/cs/psl/phosphor/struct/EnqueuedTaint;)V
    ALOAD 0
    ALOAD 3
    INVOKEVIRTUAL edu/columbia/cs/psl/phosphor/struct/ControlTaintTagStack.pop (Ledu/columbia/cs/psl/phosphor/struct/EnqueuedTaint;)V
    RETURN
   L44
    LOCALVARIABLE currDepName Ljava/lang/String; L40 L42 23
   L45
    LOCALVARIABLE phosphorJumpControlTag0 Ledu/columbia/cs/psl/phosphor/struct/ControlTaintTagStack; L1 L45 0
    LOCALVARIABLE phosphorReturnPreAlloc0 Ledu/columbia/cs/psl/phosphor/struct/TaintedDoubleWithObjTag; L3 L45 4
    LOCALVARIABLE phosphorShadowLVFor6XX2 Ledu/columbia/cs/psl/phosphor/runtime/Taint; L7 L11 7
    LOCALVARIABLE phosphorReturnPreAlloc1 Ledu/columbia/cs/psl/phosphor/struct/TaintedIntWithObjTag; L4 L45 5
    LOCALVARIABLE phosphorShadowLV11 Ledu/columbia/cs/psl/phosphor/runtime/Taint; L22 L45 15
    LOCALVARIABLE phosphorJumpControlTag3 Ledu/columbia/cs/psl/phosphor/struct/EnqueuedTaint; L1 L45 3
    LOCALVARIABLE phosphorShadowLVFor8XX3 Ledu/columbia/cs/psl/phosphor/runtime/Taint; L9 L12 9
    LOCALVARIABLE phosphorShadowLV5 Ledu/columbia/cs/psl/phosphor/runtime/Taint; L12 L45 9
    LOCALVARIABLE phosphorShadowLVFor11XX7 Ledu/columbia/cs/psl/phosphor/runtime/Taint; L15 L21 12
    LOCALVARIABLE phosphorShadowLV4 Ledu/columbia/cs/psl/phosphor/runtime/Taint; L11 L45 7
    LOCALVARIABLE phosphorShadowLV10 Ledu/columbia/cs/psl/phosphor/runtime/Taint; L21 L45 12
    LOCALVARIABLE phosphorShadowLVFor18XX13 Ledu/columbia/cs/psl/phosphor/runtime/Taint; L26 L28 19
    LOCALVARIABLE phosphorShadowLV6 I L13 L25 10
    LOCALVARIABLE phosphorShadowLV12 Ledu/columbia/cs/psl/phosphor/runtime/Taint; L24 L45 17
    LOCALVARIABLE phosphorShadowLVFor16XX9 Ledu/columbia/cs/psl/phosphor/runtime/Taint; L19 L24 17
    LOCALVARIABLE phosphorShadowLVFor13XX8 Ledu/columbia/cs/psl/phosphor/runtime/Taint; L17 L22 15
    LOCALVARIABLE phosphorJumpControlTag2 Ledu/columbia/cs/psl/phosphor/struct/EnqueuedTaint; L1 L45 2
    LOCALVARIABLE phosphorJumpControlTag1 Ledu/columbia/cs/psl/phosphor/struct/EnqueuedTaint; L1 L45 1
    LOCALVARIABLE phosphorShadowLV14 Ledu/columbia/cs/psl/phosphor/runtime/Taint; L28 L45 19
    LOCALVARIABLE x I L8 L44 6
    LOCALVARIABLE y I L10 L44 8
    LOCALVARIABLE z I L16 L44 11
    LOCALVARIABLE w D L18 L44 13
    LOCALVARIABLE n I L20 L44 16
    LOCALVARIABLE result I L27 L44 18
    LOCALVARIABLE tag Ledu/columbia/cs/psl/phosphor/runtime/Taint; L29 L44 20
    LOCALVARIABLE dependencies Ledu/columbia/cs/psl/phosphor/struct/LinkedList; L34 L44 21
    // signature Ledu/columbia/cs/psl/phosphor/struct/LinkedList<Ljava/lang/Object;>;
    // declaration: edu.columbia.cs.psl.phosphor.struct.LinkedList<java.lang.Object>
    LOCALVARIABLE currNode Ledu/columbia/cs/psl/phosphor/struct/LinkedList$Node; L36 L44 22
    MAXSTACK = 103
    MAXLOCALS = 24

  // access flags 0x9
  public static testExample5()V
   L0
   L1
    NEW edu/columbia/cs/psl/phosphor/struct/ControlTaintTagStack
    DUP
    BIPUSH 4
    INVOKESPECIAL edu/columbia/cs/psl/phosphor/struct/ControlTaintTagStack.<init> (I)V
    ASTORE 0
    ACONST_NULL
    ASTORE 1
    ACONST_NULL
    ASTORE 2
    ACONST_NULL
    ASTORE 3
    ACONST_NULL
    ASTORE 4
   L2
   L3
    NEW edu/columbia/cs/psl/phosphor/struct/TaintedIntWithObjTag
    DUP
    INVOKESPECIAL edu/columbia/cs/psl/phosphor/struct/TaintedIntWithObjTag.<init> ()V
    ASTORE 5
   L4
   L5
    LINENUMBER 88 L5
    ALOAD 0
    INVOKEVIRTUAL edu/columbia/cs/psl/phosphor/struct/ControlTaintTagStack.copyTag ()Ledu/columbia/cs/psl/phosphor/runtime/Taint;
    BIPUSH 100
    LDC "source 1"
    ALOAD 5
    INVOKESTATIC edu/columbia/cs/psl/phosphor/runtime/MultiTainter.taintedInt$$PHOSPHORTAGGED (Ledu/columbia/cs/psl/phosphor/runtime/Taint;ILjava/lang/Object;Ledu/columbia/cs/psl/phosphor/struct/TaintedIntWithObjTag;)Ledu/columbia/cs/psl/phosphor/struct/TaintedIntWithObjTag;
    DUP
    GETFIELD edu/columbia/cs/psl/phosphor/struct/TaintedIntWithObjTag.taint : Ledu/columbia/cs/psl/phosphor/runtime/Taint;
    SWAP
    GETFIELD edu/columbia/cs/psl/phosphor/struct/TaintedIntWithObjTag.val : I
    SWAP
    ALOAD 0
    INVOKESTATIC edu/columbia/cs/psl/phosphor/runtime/Taint.combineTags (Ledu/columbia/cs/psl/phosphor/runtime/Taint;Ledu/columbia/cs/psl/phosphor/struct/ControlTaintTagStack;)Ledu/columbia/cs/psl/phosphor/runtime/Taint;
    SWAP
   L6
    ISTORE 6
    INVOKESTATIC edu/columbia/cs/psl/phosphor/runtime/Taint.copyTaint (Ledu/columbia/cs/psl/phosphor/runtime/Taint;)Ledu/columbia/cs/psl/phosphor/runtime/Taint;
    ASTORE 7
   L7
    LINENUMBER 91 L7
    ALOAD 0
    INVOKEVIRTUAL edu/columbia/cs/psl/phosphor/struct/ControlTaintTagStack.copyTag ()Ledu/columbia/cs/psl/phosphor/runtime/Taint;
    BIPUSH 100
   L8
    NEW edu/columbia/cs/psl/phosphor/runtime/Taint
    DUP
    LDC "source 2"
    INVOKESPECIAL edu/columbia/cs/psl/phosphor/runtime/Taint.<init> (Ljava/lang/Object;)V
    ALOAD 5
    INVOKESTATIC edu/columbia/cs/psl/phosphor/runtime/MultiTainter.taintedInt$$PHOSPHORTAGGED (Ledu/columbia/cs/psl/phosphor/runtime/Taint;ILjava/lang/Object;Ledu/columbia/cs/psl/phosphor/struct/TaintedIntWithObjTag;)Ledu/columbia/cs/psl/phosphor/struct/TaintedIntWithObjTag;
    DUP
    GETFIELD edu/columbia/cs/psl/phosphor/struct/TaintedIntWithObjTag.taint : Ledu/columbia/cs/psl/phosphor/runtime/Taint;
    SWAP
    GETFIELD edu/columbia/cs/psl/phosphor/struct/TaintedIntWithObjTag.val : I
    SWAP
    ALOAD 0
    INVOKESTATIC edu/columbia/cs/psl/phosphor/runtime/Taint.combineTags (Ledu/columbia/cs/psl/phosphor/runtime/Taint;Ledu/columbia/cs/psl/phosphor/struct/ControlTaintTagStack;)Ledu/columbia/cs/psl/phosphor/runtime/Taint;
    SWAP
   L9
    ISTORE 8
    INVOKESTATIC edu/columbia/cs/psl/phosphor/runtime/Taint.copyTaint (Ledu/columbia/cs/psl/phosphor/runtime/Taint;)Ledu/columbia/cs/psl/phosphor/runtime/Taint;
    ASTORE 9
   L10
    LINENUMBER 93 L10
   L11
    ALOAD 7
    ILOAD 6
   L12
    ALOAD 9
    ILOAD 8
   L13
    ISTORE 10
    SWAP
    ILOAD 10
   L14
    IADD
    DUP_X2
    POP
    INVOKESTATIC edu/columbia/cs/psl/phosphor/runtime/Taint.combineTags (Ledu/columbia/cs/psl/phosphor/runtime/Taint;Ledu/columbia/cs/psl/phosphor/runtime/Taint;)Ledu/columbia/cs/psl/phosphor/runtime/Taint;
    SWAP
    SWAP
    ALOAD 0
    INVOKESTATIC edu/columbia/cs/psl/phosphor/runtime/Taint.combineTags (Ledu/columbia/cs/psl/phosphor/runtime/Taint;Ledu/columbia/cs/psl/phosphor/struct/ControlTaintTagStack;)Ledu/columbia/cs/psl/phosphor/runtime/Taint;
    SWAP
   L15
    ISTORE 11
    INVOKESTATIC edu/columbia/cs/psl/phosphor/runtime/Taint.copyTaint (Ledu/columbia/cs/psl/phosphor/runtime/Taint;)Ledu/columbia/cs/psl/phosphor/runtime/Taint;
    ASTORE 12
   L16
    LINENUMBER 95 L16
   L17
    ALOAD 12
    ILOAD 11
    INVOKESTATIC edu/columbia/cs/psl/phosphor/runtime/RuntimeBoxUnboxPropogator.toString$$PHOSPHORTAGGED (Ledu/columbia/cs/psl/phosphor/runtime/Taint;I)Ljava/lang/String;
    ASTORE 13
   L18
    LINENUMBER 96 L18
    ALOAD 13
    INVOKESTATIC edu/columbia/cs/psl/phosphor/runtime/MultiTainter.getTaint (Ljava/lang/Object;)Ledu/columbia/cs/psl/phosphor/runtime/Taint;
    ASTORE 14
   L19
    LINENUMBER 97 L19
   L20
    ALOAD 12
    ILOAD 11
    INVOKESTATIC edu/columbia/cs/psl/phosphor/runtime/MultiTainter.getTaint$$PHOSPHORTAGGED (Ledu/columbia/cs/psl/phosphor/runtime/Taint;I)Ledu/columbia/cs/psl/phosphor/runtime/Taint;
    ASTORE 15
   L21
    LINENUMBER 98 L21
    GETSTATIC com/josecambronero/ObjectTagExamples.$assertionsDisabledPHOSPHOR_TAG : Ledu/columbia/cs/psl/phosphor/runtime/Taint;
    GETSTATIC com/josecambronero/ObjectTagExamples.$assertionsDisabled : Z
    DUP
    INVOKESTATIC edu/ucdavis/cs/cyberlab/BBPhosphor/util/TaintHelper.saveTaint (Ljava/lang/Object;)V
    LDC "hello i coupied this! branching counting 1"
    INVOKESTATIC edu/ucdavis/cs/cyberlab/BBPhosphor/util/TaintHelper.printx (Ljava/lang/String;)V
    SWAP
    ALOAD 0
    SWAP
    ALOAD 1
    INVOKEVIRTUAL edu/columbia/cs/psl/phosphor/struct/ControlTaintTagStack.push (Ledu/columbia/cs/psl/phosphor/runtime/Taint;Ledu/columbia/cs/psl/phosphor/struct/EnqueuedTaint;)Ledu/columbia/cs/psl/phosphor/struct/EnqueuedTaint;
    ASTORE 1
    IFNE L22
   L23
    ALOAD 15
    IFNONNULL L22
   L24
   L25
    NEW java/lang/AssertionError
    DUP
    INVOKESPECIAL java/lang/AssertionError.<init> ()V
    DUP
    ALOAD 0
    INVOKESTATIC edu/columbia/cs/psl/phosphor/runtime/Taint.combineTagsOnObject (Ljava/lang/Object;Ledu/columbia/cs/psl/phosphor/struct/ControlTaintTagStack;)V
    ALOAD 0
    ALOAD 1
    INVOKEVIRTUAL edu/columbia/cs/psl/phosphor/struct/ControlTaintTagStack.pop (Ledu/columbia/cs/psl/phosphor/struct/EnqueuedTaint;)V
    ALOAD 0
    ALOAD 2
    INVOKEVIRTUAL edu/columbia/cs/psl/phosphor/struct/ControlTaintTagStack.pop (Ledu/columbia/cs/psl/phosphor/struct/EnqueuedTaint;)V
    ATHROW
   L22
    LINENUMBER 100 L22
   FRAME FULL [edu/columbia/cs/psl/phosphor/struct/ControlTaintTagStack edu/columbia/cs/psl/phosphor/struct/EnqueuedTaint edu/columbia/cs/psl/phosphor/struct/EnqueuedTaint edu/columbia/cs/psl/phosphor/struct/EnqueuedTaint edu/columbia/cs/psl/phosphor/struct/EnqueuedTaint edu/columbia/cs/psl/phosphor/struct/TaintedIntWithObjTag I edu/columbia/cs/psl/phosphor/runtime/Taint I edu/columbia/cs/psl/phosphor/runtime/Taint T I edu/columbia/cs/psl/phosphor/runtime/Taint java/lang/String edu/columbia/cs/psl/phosphor/runtime/Taint edu/columbia/cs/psl/phosphor/runtime/Taint] []
    GETSTATIC com/josecambronero/ObjectTagExamples.$assertionsDisabledPHOSPHOR_TAG : Ledu/columbia/cs/psl/phosphor/runtime/Taint;
    GETSTATIC com/josecambronero/ObjectTagExamples.$assertionsDisabled : Z
    DUP
    INVOKESTATIC edu/ucdavis/cs/cyberlab/BBPhosphor/util/TaintHelper.saveTaint (Ljava/lang/Object;)V
    LDC "hello i coupied this! branching counting 3"
    INVOKESTATIC edu/ucdavis/cs/cyberlab/BBPhosphor/util/TaintHelper.printx (Ljava/lang/String;)V
    SWAP
    ALOAD 0
    SWAP
    ALOAD 3
    INVOKEVIRTUAL edu/columbia/cs/psl/phosphor/struct/ControlTaintTagStack.push (Ledu/columbia/cs/psl/phosphor/runtime/Taint;Ledu/columbia/cs/psl/phosphor/struct/EnqueuedTaint;)Ledu/columbia/cs/psl/phosphor/struct/EnqueuedTaint;
    ASTORE 3
    IFNE L26
   L27
    ALOAD 14
    IFNONNULL L26
   L28
   L29
    NEW java/lang/AssertionError
    DUP
    INVOKESPECIAL java/lang/AssertionError.<init> ()V
    DUP
    ALOAD 0
    INVOKESTATIC edu/columbia/cs/psl/phosphor/runtime/Taint.combineTagsOnObject (Ljava/lang/Object;Ledu/columbia/cs/psl/phosphor/struct/ControlTaintTagStack;)V
    ALOAD 0
    ALOAD 4
    INVOKEVIRTUAL edu/columbia/cs/psl/phosphor/struct/ControlTaintTagStack.pop (Ledu/columbia/cs/psl/phosphor/struct/EnqueuedTaint;)V
    ALOAD 0
    ALOAD 1
    INVOKEVIRTUAL edu/columbia/cs/psl/phosphor/struct/ControlTaintTagStack.pop (Ledu/columbia/cs/psl/phosphor/struct/EnqueuedTaint;)V
    ALOAD 0
    ALOAD 2
    INVOKEVIRTUAL edu/columbia/cs/psl/phosphor/struct/ControlTaintTagStack.pop (Ledu/columbia/cs/psl/phosphor/struct/EnqueuedTaint;)V
    ALOAD 0
    ALOAD 3
    INVOKEVIRTUAL edu/columbia/cs/psl/phosphor/struct/ControlTaintTagStack.pop (Ledu/columbia/cs/psl/phosphor/struct/EnqueuedTaint;)V
    ATHROW
   L26
    LINENUMBER 101 L26
   FRAME FULL [edu/columbia/cs/psl/phosphor/struct/ControlTaintTagStack edu/columbia/cs/psl/phosphor/struct/EnqueuedTaint edu/columbia/cs/psl/phosphor/struct/EnqueuedTaint edu/columbia/cs/psl/phosphor/struct/EnqueuedTaint edu/columbia/cs/psl/phosphor/struct/EnqueuedTaint edu/columbia/cs/psl/phosphor/struct/TaintedIntWithObjTag I edu/columbia/cs/psl/phosphor/runtime/Taint I edu/columbia/cs/psl/phosphor/runtime/Taint T I edu/columbia/cs/psl/phosphor/runtime/Taint java/lang/String edu/columbia/cs/psl/phosphor/runtime/Taint edu/columbia/cs/psl/phosphor/runtime/Taint] []
    GETSTATIC java/lang/System.out : Ljava/io/PrintStream;
    ALOAD 15
    INVOKEVIRTUAL edu/columbia/cs/psl/phosphor/runtime/Taint.toString ()Ljava/lang/String;
    INVOKEVIRTUAL java/io/PrintStream.println (Ljava/lang/String;)V
   L30
    LINENUMBER 103 L30
    GETSTATIC java/lang/System.out : Ljava/io/PrintStream;
    ALOAD 14
    INVOKEVIRTUAL edu/columbia/cs/psl/phosphor/runtime/Taint.toString ()Ljava/lang/String;
    INVOKEVIRTUAL java/io/PrintStream.println (Ljava/lang/String;)V
   L31
    LINENUMBER 104 L31
    ALOAD 0
    ALOAD 4
    INVOKEVIRTUAL edu/columbia/cs/psl/phosphor/struct/ControlTaintTagStack.pop (Ledu/columbia/cs/psl/phosphor/struct/EnqueuedTaint;)V
    ALOAD 0
    ALOAD 1
    INVOKEVIRTUAL edu/columbia/cs/psl/phosphor/struct/ControlTaintTagStack.pop (Ledu/columbia/cs/psl/phosphor/struct/EnqueuedTaint;)V
    ALOAD 0
    ALOAD 2
    INVOKEVIRTUAL edu/columbia/cs/psl/phosphor/struct/ControlTaintTagStack.pop (Ledu/columbia/cs/psl/phosphor/struct/EnqueuedTaint;)V
    ALOAD 0
    ALOAD 3
    INVOKEVIRTUAL edu/columbia/cs/psl/phosphor/struct/ControlTaintTagStack.pop (Ledu/columbia/cs/psl/phosphor/struct/EnqueuedTaint;)V
    RETURN
   L32
    LOCALVARIABLE x I L7 L32 6
   L33
    LOCALVARIABLE phosphorShadowLV7 Ledu/columbia/cs/psl/phosphor/runtime/Taint; L17 L20 12
    LOCALVARIABLE phosphorShadowLVFor6XX1 Ledu/columbia/cs/psl/phosphor/runtime/Taint; L6 L11 7
    LOCALVARIABLE phosphorJumpControlTag1 Ledu/columbia/cs/psl/phosphor/struct/EnqueuedTaint; L1 L33 1
    LOCALVARIABLE phosphorJumpControlTag2 Ledu/columbia/cs/psl/phosphor/struct/EnqueuedTaint; L1 L33 2
    LOCALVARIABLE phosphorJumpControlTag4 Ledu/columbia/cs/psl/phosphor/struct/EnqueuedTaint; L1 L33 4
    LOCALVARIABLE phosphorShadowLVFor8XX2 Ledu/columbia/cs/psl/phosphor/runtime/Taint; L9 L12 9
    LOCALVARIABLE phosphorShadowLV3 Ledu/columbia/cs/psl/phosphor/runtime/Taint; L11 L33 7
    LOCALVARIABLE phosphorShadowLVFor11XX6 Ledu/columbia/cs/psl/phosphor/runtime/Taint; L15 L17 12
    LOCALVARIABLE phosphorShadowLV5 I L13 L14 10
    LOCALVARIABLE phosphorShadowLV8 Ledu/columbia/cs/psl/phosphor/runtime/Taint; L20 L33 12
    LOCALVARIABLE phosphorJumpControlTag3 Ledu/columbia/cs/psl/phosphor/struct/EnqueuedTaint; L1 L33 3
    LOCALVARIABLE phosphorReturnPreAlloc0 Ledu/columbia/cs/psl/phosphor/struct/TaintedIntWithObjTag; L3 L33 5
    LOCALVARIABLE phosphorJumpControlTag0 Ledu/columbia/cs/psl/phosphor/struct/ControlTaintTagStack; L1 L33 0
    LOCALVARIABLE phosphorShadowLV4 Ledu/columbia/cs/psl/phosphor/runtime/Taint; L12 L33 9
    LOCALVARIABLE y I L10 L32 8
    LOCALVARIABLE z I L16 L32 11
    LOCALVARIABLE zs Ljava/lang/String; L18 L32 13
    LOCALVARIABLE tzs Ledu/columbia/cs/psl/phosphor/runtime/Taint; L19 L32 14
    LOCALVARIABLE tz Ledu/columbia/cs/psl/phosphor/runtime/Taint; L21 L32 15
    MAXSTACK = 104
    MAXLOCALS = 16

  // access flags 0x9
  public static testExample6()V
   L0
   L1
    NEW edu/columbia/cs/psl/phosphor/struct/ControlTaintTagStack
    DUP
    BIPUSH 7
    INVOKESPECIAL edu/columbia/cs/psl/phosphor/struct/ControlTaintTagStack.<init> (I)V
    ASTORE 0
    ACONST_NULL
    ASTORE 1
    ACONST_NULL
    ASTORE 2
    ACONST_NULL
    ASTORE 3
    ACONST_NULL
    ASTORE 4
    ACONST_NULL
    ASTORE 5
    ACONST_NULL
    ASTORE 6
    ACONST_NULL
    ASTORE 7
   L2
   L3
    NEW edu/columbia/cs/psl/phosphor/struct/TaintedIntWithObjTag
    DUP
    INVOKESPECIAL edu/columbia/cs/psl/phosphor/struct/TaintedIntWithObjTag.<init> ()V
    ASTORE 8
   L4
   L5
    LINENUMBER 110 L5
    ALOAD 0
    INVOKEVIRTUAL edu/columbia/cs/psl/phosphor/struct/ControlTaintTagStack.copyTag ()Ledu/columbia/cs/psl/phosphor/runtime/Taint;
    BIPUSH 100
    LDC "source 1"
    ALOAD 8
    INVOKESTATIC edu/columbia/cs/psl/phosphor/runtime/MultiTainter.taintedInt$$PHOSPHORTAGGED (Ledu/columbia/cs/psl/phosphor/runtime/Taint;ILjava/lang/Object;Ledu/columbia/cs/psl/phosphor/struct/TaintedIntWithObjTag;)Ledu/columbia/cs/psl/phosphor/struct/TaintedIntWithObjTag;
    DUP
    GETFIELD edu/columbia/cs/psl/phosphor/struct/TaintedIntWithObjTag.taint : Ledu/columbia/cs/psl/phosphor/runtime/Taint;
    SWAP
    GETFIELD edu/columbia/cs/psl/phosphor/struct/TaintedIntWithObjTag.val : I
    SWAP
    ALOAD 0
    INVOKESTATIC edu/columbia/cs/psl/phosphor/runtime/Taint.combineTags (Ledu/columbia/cs/psl/phosphor/runtime/Taint;Ledu/columbia/cs/psl/phosphor/struct/ControlTaintTagStack;)Ledu/columbia/cs/psl/phosphor/runtime/Taint;
    SWAP
   L6
    ISTORE 9
    INVOKESTATIC edu/columbia/cs/psl/phosphor/runtime/Taint.copyTaint (Ledu/columbia/cs/psl/phosphor/runtime/Taint;)Ledu/columbia/cs/psl/phosphor/runtime/Taint;
    ASTORE 10
   L7
    LINENUMBER 113 L7
    ALOAD 0
    INVOKEVIRTUAL edu/columbia/cs/psl/phosphor/struct/ControlTaintTagStack.copyTag ()Ledu/columbia/cs/psl/phosphor/runtime/Taint;
    BIPUSH 100
   L8
    NEW edu/columbia/cs/psl/phosphor/runtime/Taint
    DUP
    LDC "source 2"
    INVOKESPECIAL edu/columbia/cs/psl/phosphor/runtime/Taint.<init> (Ljava/lang/Object;)V
    ALOAD 8
    INVOKESTATIC edu/columbia/cs/psl/phosphor/runtime/MultiTainter.taintedInt$$PHOSPHORTAGGED (Ledu/columbia/cs/psl/phosphor/runtime/Taint;ILjava/lang/Object;Ledu/columbia/cs/psl/phosphor/struct/TaintedIntWithObjTag;)Ledu/columbia/cs/psl/phosphor/struct/TaintedIntWithObjTag;
    DUP
    GETFIELD edu/columbia/cs/psl/phosphor/struct/TaintedIntWithObjTag.taint : Ledu/columbia/cs/psl/phosphor/runtime/Taint;
    SWAP
    GETFIELD edu/columbia/cs/psl/phosphor/struct/TaintedIntWithObjTag.val : I
    SWAP
    ALOAD 0
    INVOKESTATIC edu/columbia/cs/psl/phosphor/runtime/Taint.combineTags (Ledu/columbia/cs/psl/phosphor/runtime/Taint;Ledu/columbia/cs/psl/phosphor/struct/ControlTaintTagStack;)Ledu/columbia/cs/psl/phosphor/runtime/Taint;
    SWAP
   L9
    ISTORE 11
    INVOKESTATIC edu/columbia/cs/psl/phosphor/runtime/Taint.copyTaint (Ledu/columbia/cs/psl/phosphor/runtime/Taint;)Ledu/columbia/cs/psl/phosphor/runtime/Taint;
    ASTORE 12
   L10
    LINENUMBER 115 L10
   L11
    ALOAD 10
    ILOAD 9
   L12
    ALOAD 12
    ILOAD 11
   L13
    ISTORE 13
    SWAP
    ILOAD 13
   L14
    IADD
    DUP_X2
    POP
    INVOKESTATIC edu/columbia/cs/psl/phosphor/runtime/Taint.combineTags (Ledu/columbia/cs/psl/phosphor/runtime/Taint;Ledu/columbia/cs/psl/phosphor/runtime/Taint;)Ledu/columbia/cs/psl/phosphor/runtime/Taint;
    SWAP
    SWAP
    ALOAD 0
    INVOKESTATIC edu/columbia/cs/psl/phosphor/runtime/Taint.combineTags (Ledu/columbia/cs/psl/phosphor/runtime/Taint;Ledu/columbia/cs/psl/phosphor/struct/ControlTaintTagStack;)Ledu/columbia/cs/psl/phosphor/runtime/Taint;
    SWAP
   L15
    ISTORE 14
    INVOKESTATIC edu/columbia/cs/psl/phosphor/runtime/Taint.copyTaint (Ledu/columbia/cs/psl/phosphor/runtime/Taint;)Ledu/columbia/cs/psl/phosphor/runtime/Taint;
    ASTORE 15
   L16
    LINENUMBER 116 L16
   L17
    ALOAD 15
    ILOAD 14
    DUP
    INVOKESTATIC edu/ucdavis/cs/cyberlab/BBPhosphor/util/TaintHelper.saveTaint (Ljava/lang/Object;)V
    LDC "hello i coupied this! branching counting 1"
    INVOKESTATIC edu/ucdavis/cs/cyberlab/BBPhosphor/util/TaintHelper.printx (Ljava/lang/String;)V
    SWAP
    ALOAD 0
    SWAP
    ALOAD 1
    INVOKEVIRTUAL edu/columbia/cs/psl/phosphor/struct/ControlTaintTagStack.push (Ledu/columbia/cs/psl/phosphor/runtime/Taint;Ledu/columbia/cs/psl/phosphor/struct/EnqueuedTaint;)Ledu/columbia/cs/psl/phosphor/struct/EnqueuedTaint;
    ASTORE 1
    IFLE L18
   L19
   L20
    LINENUMBER 118 L20
    GETSTATIC java/lang/System.out : Ljava/io/PrintStream;
   L21
    ALOAD 15
    ILOAD 14
    INVOKEVIRTUAL java/io/PrintStream.println$$PHOSPHORTAGGED (Ledu/columbia/cs/psl/phosphor/runtime/Taint;I)V
   L18
    LINENUMBER 121 L18
   FRAME FULL [edu/columbia/cs/psl/phosphor/struct/ControlTaintTagStack edu/columbia/cs/psl/phosphor/struct/EnqueuedTaint edu/columbia/cs/psl/phosphor/struct/EnqueuedTaint edu/columbia/cs/psl/phosphor/struct/EnqueuedTaint edu/columbia/cs/psl/phosphor/struct/EnqueuedTaint edu/columbia/cs/psl/phosphor/struct/EnqueuedTaint edu/columbia/cs/psl/phosphor/struct/EnqueuedTaint edu/columbia/cs/psl/phosphor/struct/EnqueuedTaint edu/columbia/cs/psl/phosphor/struct/TaintedIntWithObjTag I edu/columbia/cs/psl/phosphor/runtime/Taint I edu/columbia/cs/psl/phosphor/runtime/Taint T I edu/columbia/cs/psl/phosphor/runtime/Taint] []
    ALOAD 0
    ALOAD 1
    INVOKEVIRTUAL edu/columbia/cs/psl/phosphor/struct/ControlTaintTagStack.pop (Ledu/columbia/cs/psl/phosphor/struct/EnqueuedTaint;)V
   L22
    ALOAD 10
    ILOAD 9
   L23
    ALOAD 12
    ILOAD 11
    SWAP
    ASTORE 13
    DUP2_X1
    POP2
    ALOAD 0
    SWAP
    ALOAD 0
    ALOAD 13
   L24
    ALOAD 2
    INVOKEVIRTUAL edu/columbia/cs/psl/phosphor/struct/ControlTaintTagStack.push (Ledu/columbia/cs/psl/phosphor/runtime/Taint;Ledu/columbia/cs/psl/phosphor/struct/EnqueuedTaint;)Ledu/columbia/cs/psl/phosphor/struct/EnqueuedTaint;
    ASTORE 2
    ALOAD 3
    INVOKEVIRTUAL edu/columbia/cs/psl/phosphor/struct/ControlTaintTagStack.push (Ledu/columbia/cs/psl/phosphor/runtime/Taint;Ledu/columbia/cs/psl/phosphor/struct/EnqueuedTaint;)Ledu/columbia/cs/psl/phosphor/struct/EnqueuedTaint;
    ASTORE 3
    IF_ICMPGE L25
   L26
   L27
    LINENUMBER 122 L27
    GETSTATIC java/lang/System.out : Ljava/io/PrintStream;
   L28
    ALOAD 10
    ILOAD 9
    INVOKEVIRTUAL java/io/PrintStream.println$$PHOSPHORTAGGED (Ledu/columbia/cs/psl/phosphor/runtime/Taint;I)V
   L25
    LINENUMBER 125 L25
   FRAME FULL [edu/columbia/cs/psl/phosphor/struct/ControlTaintTagStack edu/columbia/cs/psl/phosphor/struct/EnqueuedTaint edu/columbia/cs/psl/phosphor/struct/EnqueuedTaint edu/columbia/cs/psl/phosphor/struct/EnqueuedTaint edu/columbia/cs/psl/phosphor/struct/EnqueuedTaint edu/columbia/cs/psl/phosphor/struct/EnqueuedTaint edu/columbia/cs/psl/phosphor/struct/EnqueuedTaint edu/columbia/cs/psl/phosphor/struct/EnqueuedTaint edu/columbia/cs/psl/phosphor/struct/TaintedIntWithObjTag I edu/columbia/cs/psl/phosphor/runtime/Taint I edu/columbia/cs/psl/phosphor/runtime/Taint T I edu/columbia/cs/psl/phosphor/runtime/Taint] []
    ALOAD 0
    ALOAD 2
    INVOKEVIRTUAL edu/columbia/cs/psl/phosphor/struct/ControlTaintTagStack.pop (Ledu/columbia/cs/psl/phosphor/struct/EnqueuedTaint;)V
    ALOAD 0
    ALOAD 3
    INVOKEVIRTUAL edu/columbia/cs/psl/phosphor/struct/ControlTaintTagStack.pop (Ledu/columbia/cs/psl/phosphor/struct/EnqueuedTaint;)V
   L29
    ALOAD 15
    ILOAD 14
    INVOKESTATIC edu/columbia/cs/psl/phosphor/runtime/RuntimeBoxUnboxPropogator.toString$$PHOSPHORTAGGED (Ledu/columbia/cs/psl/phosphor/runtime/Taint;I)Ljava/lang/String;
    ASTORE 16
   L30
    LINENUMBER 126 L30
    ALOAD 16
    INVOKESTATIC edu/columbia/cs/psl/phosphor/runtime/MultiTainter.getTaint (Ljava/lang/Object;)Ledu/columbia/cs/psl/phosphor/runtime/Taint;
    ASTORE 17
   L31
    LINENUMBER 127 L31
   L32
    ALOAD 15
    ILOAD 14
    INVOKESTATIC edu/columbia/cs/psl/phosphor/runtime/MultiTainter.getTaint$$PHOSPHORTAGGED (Ledu/columbia/cs/psl/phosphor/runtime/Taint;I)Ledu/columbia/cs/psl/phosphor/runtime/Taint;
    ASTORE 18
   L33
    LINENUMBER 128 L33
    GETSTATIC com/josecambronero/ObjectTagExamples.$assertionsDisabledPHOSPHOR_TAG : Ledu/columbia/cs/psl/phosphor/runtime/Taint;
    GETSTATIC com/josecambronero/ObjectTagExamples.$assertionsDisabled : Z
    DUP
    INVOKESTATIC edu/ucdavis/cs/cyberlab/BBPhosphor/util/TaintHelper.saveTaint (Ljava/lang/Object;)V
    LDC "hello i coupied this! branching counting 4"
    INVOKESTATIC edu/ucdavis/cs/cyberlab/BBPhosphor/util/TaintHelper.printx (Ljava/lang/String;)V
    SWAP
    ALOAD 0
    SWAP
    ALOAD 4
    INVOKEVIRTUAL edu/columbia/cs/psl/phosphor/struct/ControlTaintTagStack.push (Ledu/columbia/cs/psl/phosphor/runtime/Taint;Ledu/columbia/cs/psl/phosphor/struct/EnqueuedTaint;)Ledu/columbia/cs/psl/phosphor/struct/EnqueuedTaint;
    ASTORE 4
    IFNE L34
   L35
    ALOAD 18
    IFNONNULL L34
   L36
   L37
    NEW java/lang/AssertionError
    DUP
    INVOKESPECIAL java/lang/AssertionError.<init> ()V
    DUP
    ALOAD 0
    INVOKESTATIC edu/columbia/cs/psl/phosphor/runtime/Taint.combineTagsOnObject (Ljava/lang/Object;Ledu/columbia/cs/psl/phosphor/struct/ControlTaintTagStack;)V
    ALOAD 0
    ALOAD 4
    INVOKEVIRTUAL edu/columbia/cs/psl/phosphor/struct/ControlTaintTagStack.pop (Ledu/columbia/cs/psl/phosphor/struct/EnqueuedTaint;)V
    ALOAD 0
    ALOAD 5
    INVOKEVIRTUAL edu/columbia/cs/psl/phosphor/struct/ControlTaintTagStack.pop (Ledu/columbia/cs/psl/phosphor/struct/EnqueuedTaint;)V
    ATHROW
   L34
    LINENUMBER 130 L34
   FRAME FULL [edu/columbia/cs/psl/phosphor/struct/ControlTaintTagStack edu/columbia/cs/psl/phosphor/struct/EnqueuedTaint edu/columbia/cs/psl/phosphor/struct/EnqueuedTaint edu/columbia/cs/psl/phosphor/struct/EnqueuedTaint edu/columbia/cs/psl/phosphor/struct/EnqueuedTaint edu/columbia/cs/psl/phosphor/struct/EnqueuedTaint edu/columbia/cs/psl/phosphor/struct/EnqueuedTaint edu/columbia/cs/psl/phosphor/struct/EnqueuedTaint edu/columbia/cs/psl/phosphor/struct/TaintedIntWithObjTag I edu/columbia/cs/psl/phosphor/runtime/Taint I edu/columbia/cs/psl/phosphor/runtime/Taint T I edu/columbia/cs/psl/phosphor/runtime/Taint java/lang/String edu/columbia/cs/psl/phosphor/runtime/Taint edu/columbia/cs/psl/phosphor/runtime/Taint] []
    GETSTATIC com/josecambronero/ObjectTagExamples.$assertionsDisabledPHOSPHOR_TAG : Ledu/columbia/cs/psl/phosphor/runtime/Taint;
    GETSTATIC com/josecambronero/ObjectTagExamples.$assertionsDisabled : Z
    DUP
    INVOKESTATIC edu/ucdavis/cs/cyberlab/BBPhosphor/util/TaintHelper.saveTaint (Ljava/lang/Object;)V
    LDC "hello i coupied this! branching counting 6"
    INVOKESTATIC edu/ucdavis/cs/cyberlab/BBPhosphor/util/TaintHelper.printx (Ljava/lang/String;)V
    SWAP
    ALOAD 0
    SWAP
    ALOAD 6
    INVOKEVIRTUAL edu/columbia/cs/psl/phosphor/struct/ControlTaintTagStack.push (Ledu/columbia/cs/psl/phosphor/runtime/Taint;Ledu/columbia/cs/psl/phosphor/struct/EnqueuedTaint;)Ledu/columbia/cs/psl/phosphor/struct/EnqueuedTaint;
    ASTORE 6
    IFNE L38
   L39
    ALOAD 17
    IFNONNULL L38
   L40
   L41
    NEW java/lang/AssertionError
    DUP
    INVOKESPECIAL java/lang/AssertionError.<init> ()V
    DUP
    ALOAD 0
    INVOKESTATIC edu/columbia/cs/psl/phosphor/runtime/Taint.combineTagsOnObject (Ljava/lang/Object;Ledu/columbia/cs/psl/phosphor/struct/ControlTaintTagStack;)V
    ALOAD 0
    ALOAD 7
    INVOKEVIRTUAL edu/columbia/cs/psl/phosphor/struct/ControlTaintTagStack.pop (Ledu/columbia/cs/psl/phosphor/struct/EnqueuedTaint;)V
    ALOAD 0
    ALOAD 6
    INVOKEVIRTUAL edu/columbia/cs/psl/phosphor/struct/ControlTaintTagStack.pop (Ledu/columbia/cs/psl/phosphor/struct/EnqueuedTaint;)V
    ALOAD 0
    ALOAD 4
    INVOKEVIRTUAL edu/columbia/cs/psl/phosphor/struct/ControlTaintTagStack.pop (Ledu/columbia/cs/psl/phosphor/struct/EnqueuedTaint;)V
    ALOAD 0
    ALOAD 5
    INVOKEVIRTUAL edu/columbia/cs/psl/phosphor/struct/ControlTaintTagStack.pop (Ledu/columbia/cs/psl/phosphor/struct/EnqueuedTaint;)V
    ATHROW
   L38
    LINENUMBER 131 L38
   FRAME FULL [edu/columbia/cs/psl/phosphor/struct/ControlTaintTagStack edu/columbia/cs/psl/phosphor/struct/EnqueuedTaint edu/columbia/cs/psl/phosphor/struct/EnqueuedTaint edu/columbia/cs/psl/phosphor/struct/EnqueuedTaint edu/columbia/cs/psl/phosphor/struct/EnqueuedTaint edu/columbia/cs/psl/phosphor/struct/EnqueuedTaint edu/columbia/cs/psl/phosphor/struct/EnqueuedTaint edu/columbia/cs/psl/phosphor/struct/EnqueuedTaint edu/columbia/cs/psl/phosphor/struct/TaintedIntWithObjTag I edu/columbia/cs/psl/phosphor/runtime/Taint I edu/columbia/cs/psl/phosphor/runtime/Taint T I edu/columbia/cs/psl/phosphor/runtime/Taint java/lang/String edu/columbia/cs/psl/phosphor/runtime/Taint edu/columbia/cs/psl/phosphor/runtime/Taint] []
    GETSTATIC java/lang/System.out : Ljava/io/PrintStream;
    ALOAD 18
    INVOKEVIRTUAL edu/columbia/cs/psl/phosphor/runtime/Taint.toString ()Ljava/lang/String;
    INVOKEVIRTUAL java/io/PrintStream.println (Ljava/lang/String;)V
   L42
    LINENUMBER 133 L42
    GETSTATIC java/lang/System.out : Ljava/io/PrintStream;
    ALOAD 17
    INVOKEVIRTUAL edu/columbia/cs/psl/phosphor/runtime/Taint.toString ()Ljava/lang/String;
    INVOKEVIRTUAL java/io/PrintStream.println (Ljava/lang/String;)V
   L43
    LINENUMBER 134 L43
    ALOAD 0
    ALOAD 7
    INVOKEVIRTUAL edu/columbia/cs/psl/phosphor/struct/ControlTaintTagStack.pop (Ledu/columbia/cs/psl/phosphor/struct/EnqueuedTaint;)V
    ALOAD 0
    ALOAD 6
    INVOKEVIRTUAL edu/columbia/cs/psl/phosphor/struct/ControlTaintTagStack.pop (Ledu/columbia/cs/psl/phosphor/struct/EnqueuedTaint;)V
    ALOAD 0
    ALOAD 4
    INVOKEVIRTUAL edu/columbia/cs/psl/phosphor/struct/ControlTaintTagStack.pop (Ledu/columbia/cs/psl/phosphor/struct/EnqueuedTaint;)V
    ALOAD 0
    ALOAD 5
    INVOKEVIRTUAL edu/columbia/cs/psl/phosphor/struct/ControlTaintTagStack.pop (Ledu/columbia/cs/psl/phosphor/struct/EnqueuedTaint;)V
    RETURN
   L44
    LOCALVARIABLE x I L7 L44 9
   L45
    LOCALVARIABLE phosphorJumpControlTag2 Ledu/columbia/cs/psl/phosphor/struct/EnqueuedTaint; L1 L45 2
    LOCALVARIABLE phosphorJumpControlTag3 Ledu/columbia/cs/psl/phosphor/struct/EnqueuedTaint; L1 L45 3
    LOCALVARIABLE phosphorShadowLV3 Ledu/columbia/cs/psl/phosphor/runtime/Taint; L11 L22 10
    LOCALVARIABLE phosphorShadowLV9 Ledu/columbia/cs/psl/phosphor/runtime/Taint; L22 L28 10
    LOCALVARIABLE phosphorJumpControlTag5 Ledu/columbia/cs/psl/phosphor/struct/EnqueuedTaint; L1 L45 5
    LOCALVARIABLE phosphorShadowLVFor9XX1 Ledu/columbia/cs/psl/phosphor/runtime/Taint; L6 L11 10
    LOCALVARIABLE phosphorShadowLV7 Ledu/columbia/cs/psl/phosphor/runtime/Taint; L17 L21 15
    LOCALVARIABLE phosphorShadowLV5 I L13 L24 13
    LOCALVARIABLE phosphorReturnPreAlloc0 Ledu/columbia/cs/psl/phosphor/struct/TaintedIntWithObjTag; L3 L45 8
    LOCALVARIABLE phosphorShadowLV8 Ledu/columbia/cs/psl/phosphor/runtime/Taint; L21 L29 15
    LOCALVARIABLE phosphorShadowLV4 Ledu/columbia/cs/psl/phosphor/runtime/Taint; L12 L23 12
    LOCALVARIABLE phosphorShadowLV13 Ledu/columbia/cs/psl/phosphor/runtime/Taint; L32 L45 15
    LOCALVARIABLE phosphorJumpControlTag6 Ledu/columbia/cs/psl/phosphor/struct/EnqueuedTaint; L1 L45 6
    LOCALVARIABLE phosphorShadowLVFor11XX2 Ledu/columbia/cs/psl/phosphor/runtime/Taint; L9 L12 12
    LOCALVARIABLE phosphorShadowLV10 Ledu/columbia/cs/psl/phosphor/runtime/Taint; L23 L45 12
    LOCALVARIABLE phosphorJumpControlTag4 Ledu/columbia/cs/psl/phosphor/struct/EnqueuedTaint; L1 L45 4
    LOCALVARIABLE phosphorShadowLV11 Ledu/columbia/cs/psl/phosphor/runtime/Taint; L28 L45 10
    LOCALVARIABLE phosphorJumpControlTag0 Ledu/columbia/cs/psl/phosphor/struct/ControlTaintTagStack; L1 L45 0
    LOCALVARIABLE phosphorShadowLV12 Ledu/columbia/cs/psl/phosphor/runtime/Taint; L29 L32 15
    LOCALVARIABLE phosphorShadowLVFor14XX6 Ledu/columbia/cs/psl/phosphor/runtime/Taint; L15 L17 15
    LOCALVARIABLE phosphorJumpControlTag1 Ledu/columbia/cs/psl/phosphor/struct/EnqueuedTaint; L1 L45 1
    LOCALVARIABLE phosphorJumpControlTag7 Ledu/columbia/cs/psl/phosphor/struct/EnqueuedTaint; L1 L45 7
    LOCALVARIABLE y I L10 L44 11
    LOCALVARIABLE z I L16 L44 14
    LOCALVARIABLE zs Ljava/lang/String; L30 L44 16
    LOCALVARIABLE tzs Ledu/columbia/cs/psl/phosphor/runtime/Taint; L31 L44 17
    LOCALVARIABLE tz Ledu/columbia/cs/psl/phosphor/runtime/Taint; L33 L44 18
    MAXSTACK = 104
    MAXLOCALS = 19

  // access flags 0x9
  public static main([Ljava/lang/String;)V
   L0
   L1
    NEW edu/columbia/cs/psl/phosphor/struct/ControlTaintTagStack
    DUP
    BIPUSH 3
    INVOKESPECIAL edu/columbia/cs/psl/phosphor/struct/ControlTaintTagStack.<init> (I)V
    ASTORE 1
    ACONST_NULL
    ASTORE 2
    ACONST_NULL
    ASTORE 3
    ACONST_NULL
    ASTORE 4
   L2
   L3
    NEW edu/columbia/cs/psl/phosphor/struct/TaintedBooleanWithObjTag
    DUP
    INVOKESPECIAL edu/columbia/cs/psl/phosphor/struct/TaintedBooleanWithObjTag.<init> ()V
    ASTORE 5
    TRYCATCHBLOCK L4 L5 L6 java/lang/IllegalAccessException
    TRYCATCHBLOCK L4 L5 L7 java/lang/IllegalArgumentException
    TRYCATCHBLOCK L4 L5 L8 java/lang/reflect/InvocationTargetException
   L9
   L10
    LINENUMBER 138 L10
    LDC Lcom/josecambronero/ObjectTagExamples;.class
    INVOKEVIRTUAL java/lang/Class.getDeclaredMethods ()[Ljava/lang/reflect/Method;
    INVOKESTATIC edu/columbia/cs/psl/phosphor/runtime/ReflectionMasker.removeTaintMethods ([Ljava/lang/reflect/Method;)[Ljava/lang/reflect/Method;
    ASTORE 6
    ALOAD 6
    DUP
    POP
    ACONST_NULL
    CHECKCAST edu/columbia/cs/psl/phosphor/runtime/Taint
    SWAP
    ARRAYLENGTH
    SWAP
    ALOAD 1
    INVOKESTATIC edu/columbia/cs/psl/phosphor/runtime/Taint.combineTags (Ledu/columbia/cs/psl/phosphor/runtime/Taint;Ledu/columbia/cs/psl/phosphor/struct/ControlTaintTagStack;)Ledu/columbia/cs/psl/phosphor/runtime/Taint;
    SWAP
   L11
    ISTORE 7
    INVOKESTATIC edu/columbia/cs/psl/phosphor/runtime/Taint.copyTaint (Ledu/columbia/cs/psl/phosphor/runtime/Taint;)Ledu/columbia/cs/psl/phosphor/runtime/Taint;
    ASTORE 8
    ALOAD 1
    INVOKEVIRTUAL edu/columbia/cs/psl/phosphor/struct/ControlTaintTagStack.copyTag ()Ledu/columbia/cs/psl/phosphor/runtime/Taint;
    ICONST_0
    SWAP
    ALOAD 1
    INVOKESTATIC edu/columbia/cs/psl/phosphor/runtime/Taint.combineTags (Ledu/columbia/cs/psl/phosphor/runtime/Taint;Ledu/columbia/cs/psl/phosphor/struct/ControlTaintTagStack;)Ledu/columbia/cs/psl/phosphor/runtime/Taint;
    SWAP
   L12
    ISTORE 9
    INVOKESTATIC edu/columbia/cs/psl/phosphor/runtime/Taint.copyTaint (Ledu/columbia/cs/psl/phosphor/runtime/Taint;)Ledu/columbia/cs/psl/phosphor/runtime/Taint;
    ASTORE 10
   L13
   FRAME FULL [[Ljava/lang/String; edu/columbia/cs/psl/phosphor/struct/ControlTaintTagStack edu/columbia/cs/psl/phosphor/struct/EnqueuedTaint edu/columbia/cs/psl/phosphor/struct/EnqueuedTaint edu/columbia/cs/psl/phosphor/struct/EnqueuedTaint edu/columbia/cs/psl/phosphor/struct/TaintedBooleanWithObjTag [Ljava/lang/reflect/Method; I edu/columbia/cs/psl/phosphor/runtime/Taint I edu/columbia/cs/psl/phosphor/runtime/Taint] []
    ALOAD 1
    ALOAD 4
    INVOKEVIRTUAL edu/columbia/cs/psl/phosphor/struct/ControlTaintTagStack.pop (Ledu/columbia/cs/psl/phosphor/struct/EnqueuedTaint;)V
   L14
    ALOAD 10
    ILOAD 9
   L15
    ALOAD 8
    ILOAD 7
   L16
    SWAP
    ASTORE 11
    DUP2_X1
    POP2
    ALOAD 1
    SWAP
    ALOAD 1
    ALOAD 11
   L17
    ALOAD 2
    INVOKEVIRTUAL edu/columbia/cs/psl/phosphor/struct/ControlTaintTagStack.push (Ledu/columbia/cs/psl/phosphor/runtime/Taint;Ledu/columbia/cs/psl/phosphor/struct/EnqueuedTaint;)Ledu/columbia/cs/psl/phosphor/struct/EnqueuedTaint;
    ASTORE 2
    ALOAD 3
    INVOKEVIRTUAL edu/columbia/cs/psl/phosphor/struct/ControlTaintTagStack.push (Ledu/columbia/cs/psl/phosphor/runtime/Taint;Ledu/columbia/cs/psl/phosphor/struct/EnqueuedTaint;)Ledu/columbia/cs/psl/phosphor/struct/EnqueuedTaint;
    ASTORE 3
    IF_ICMPGE L18
   L19
    ALOAD 6
    ILOAD 9
    AALOAD
    ASTORE 12
   L20
    LINENUMBER 139 L20
    ALOAD 12
    ICONST_1
    INVOKESTATIC edu/columbia/cs/psl/phosphor/runtime/ReflectionMasker.getOrigMethod (Ljava/lang/reflect/Method;Z)Ljava/lang/reflect/Method;
    INVOKEVIRTUAL java/lang/reflect/Method.getName ()Ljava/lang/String;
    LDC "test"
    ALOAD 5
    INVOKEVIRTUAL java/lang/String.startsWith$$PHOSPHORTAGGED (Ljava/lang/String;Ledu/columbia/cs/psl/phosphor/struct/TaintedBooleanWithObjTag;)Ledu/columbia/cs/psl/phosphor/struct/TaintedBooleanWithObjTag;
    DUP
    GETFIELD edu/columbia/cs/psl/phosphor/struct/TaintedBooleanWithObjTag.taint : Ledu/columbia/cs/psl/phosphor/runtime/Taint;
    SWAP
    GETFIELD edu/columbia/cs/psl/phosphor/struct/TaintedBooleanWithObjTag.val : Z
    DUP
    INVOKESTATIC edu/ucdavis/cs/cyberlab/BBPhosphor/util/TaintHelper.saveTaint (Ljava/lang/Object;)V
    LDC "hello i coupied this! branching counting 3"
    INVOKESTATIC edu/ucdavis/cs/cyberlab/BBPhosphor/util/TaintHelper.printx (Ljava/lang/String;)V
    SWAP
    ALOAD 1
    SWAP
    ALOAD 4
    INVOKEVIRTUAL edu/columbia/cs/psl/phosphor/struct/ControlTaintTagStack.push (Ledu/columbia/cs/psl/phosphor/runtime/Taint;Ledu/columbia/cs/psl/phosphor/struct/EnqueuedTaint;)Ledu/columbia/cs/psl/phosphor/struct/EnqueuedTaint;
    ASTORE 4
    IFEQ L21
   L22
   L23
    LINENUMBER 140 L23
    GETSTATIC java/lang/System.out : Ljava/io/PrintStream;
    ALOAD 12
    ICONST_1
    INVOKESTATIC edu/columbia/cs/psl/phosphor/runtime/ReflectionMasker.getOrigMethod (Ljava/lang/reflect/Method;Z)Ljava/lang/reflect/Method;
    INVOKEVIRTUAL java/lang/reflect/Method.getName ()Ljava/lang/String;
    INVOKEVIRTUAL java/io/PrintStream.println (Ljava/lang/String;)V
   L4
    LINENUMBER 142 L4
    ALOAD 12
    ACONST_NULL
    ICONST_0
    ANEWARRAY java/lang/Object
    ICONST_1
    INVOKESTATIC edu/columbia/cs/psl/phosphor/runtime/ReflectionMasker.fixAllArgs (Ljava/lang/reflect/Method;Ljava/lang/Object;[Ljava/lang/Object;Z)Ledu/columbia/cs/psl/phosphor/struct/MethodInvoke;
    DUP
    GETFIELD edu/columbia/cs/psl/phosphor/struct/MethodInvoke.m : Ljava/lang/reflect/Method;
    SWAP
    DUP
    GETFIELD edu/columbia/cs/psl/phosphor/struct/MethodInvoke.o : Ljava/lang/Object;
    SWAP
    GETFIELD edu/columbia/cs/psl/phosphor/struct/MethodInvoke.a : [Ljava/lang/Object;
    INVOKEVIRTUAL java/lang/reflect/Method.invoke (Ljava/lang/Object;[Ljava/lang/Object;)Ljava/lang/Object;
    DUP
    INSTANCEOF edu/columbia/cs/psl/phosphor/struct/TaintedPrimitiveWithObjTag
    IFEQ L24
    CHECKCAST edu/columbia/cs/psl/phosphor/struct/TaintedPrimitiveWithObjTag
    INVOKEVIRTUAL edu/columbia/cs/psl/phosphor/struct/TaintedPrimitiveWithObjTag.toPrimitiveType ()Ljava/lang/Object;
   L24
   FRAME FULL [[Ljava/lang/String; edu/columbia/cs/psl/phosphor/struct/ControlTaintTagStack edu/columbia/cs/psl/phosphor/struct/EnqueuedTaint edu/columbia/cs/psl/phosphor/struct/EnqueuedTaint edu/columbia/cs/psl/phosphor/struct/EnqueuedTaint edu/columbia/cs/psl/phosphor/struct/TaintedBooleanWithObjTag [Ljava/lang/reflect/Method; I edu/columbia/cs/psl/phosphor/runtime/Taint I edu/columbia/cs/psl/phosphor/runtime/Taint T java/lang/reflect/Method] [java/lang/Object]
    POP
   L5
    LINENUMBER 152 L5
    GOTO L21
   L25
   L6
    LINENUMBER 143 L6
   FRAME FULL [[Ljava/lang/String; edu/columbia/cs/psl/phosphor/struct/ControlTaintTagStack edu/columbia/cs/psl/phosphor/struct/EnqueuedTaint edu/columbia/cs/psl/phosphor/struct/EnqueuedTaint edu/columbia/cs/psl/phosphor/struct/EnqueuedTaint edu/columbia/cs/psl/phosphor/struct/TaintedBooleanWithObjTag [Ljava/lang/reflect/Method; I edu/columbia/cs/psl/phosphor/runtime/Taint I edu/columbia/cs/psl/phosphor/runtime/Taint T java/lang/reflect/Method] [java/lang/IllegalAccessException]
    ASTORE 13
   L26
    LINENUMBER 145 L26
    ALOAD 13
    INVOKEVIRTUAL java/lang/IllegalAccessException.printStackTrace ()V
   L27
    LINENUMBER 152 L27
    GOTO L21
   L28
   L7
    LINENUMBER 146 L7
   FRAME FULL [[Ljava/lang/String; edu/columbia/cs/psl/phosphor/struct/ControlTaintTagStack edu/columbia/cs/psl/phosphor/struct/EnqueuedTaint edu/columbia/cs/psl/phosphor/struct/EnqueuedTaint edu/columbia/cs/psl/phosphor/struct/EnqueuedTaint edu/columbia/cs/psl/phosphor/struct/TaintedBooleanWithObjTag [Ljava/lang/reflect/Method; I edu/columbia/cs/psl/phosphor/runtime/Taint I edu/columbia/cs/psl/phosphor/runtime/Taint T java/lang/reflect/Method] [java/lang/IllegalArgumentException]
    ASTORE 13
   L29
    LINENUMBER 148 L29
    ALOAD 13
    INVOKEVIRTUAL java/lang/IllegalArgumentException.printStackTrace ()V
   L30
    LINENUMBER 152 L30
    GOTO L21
   L31
   L8
    LINENUMBER 149 L8
   FRAME FULL [[Ljava/lang/String; edu/columbia/cs/psl/phosphor/struct/ControlTaintTagStack edu/columbia/cs/psl/phosphor/struct/EnqueuedTaint edu/columbia/cs/psl/phosphor/struct/EnqueuedTaint edu/columbia/cs/psl/phosphor/struct/EnqueuedTaint edu/columbia/cs/psl/phosphor/struct/TaintedBooleanWithObjTag [Ljava/lang/reflect/Method; I edu/columbia/cs/psl/phosphor/runtime/Taint I edu/columbia/cs/psl/phosphor/runtime/Taint T java/lang/reflect/Method] [java/lang/reflect/InvocationTargetException]
    ASTORE 13
   L32
    LINENUMBER 151 L32
    ALOAD 13
    INVOKEVIRTUAL java/lang/reflect/InvocationTargetException.printStackTrace ()V
   L21
    LINENUMBER 138 L21
   FRAME FULL [[Ljava/lang/String; edu/columbia/cs/psl/phosphor/struct/ControlTaintTagStack edu/columbia/cs/psl/phosphor/struct/EnqueuedTaint edu/columbia/cs/psl/phosphor/struct/EnqueuedTaint edu/columbia/cs/psl/phosphor/struct/EnqueuedTaint edu/columbia/cs/psl/phosphor/struct/TaintedBooleanWithObjTag [Ljava/lang/reflect/Method; I edu/columbia/cs/psl/phosphor/runtime/Taint I edu/columbia/cs/psl/phosphor/runtime/Taint] []
    ALOAD 10
    ALOAD 1
    INVOKESTATIC edu/columbia/cs/psl/phosphor/runtime/Taint.combineTags (Ledu/columbia/cs/psl/phosphor/runtime/Taint;Ledu/columbia/cs/psl/phosphor/struct/ControlTaintTagStack;)Ledu/columbia/cs/psl/phosphor/runtime/Taint;
    ASTORE 10
    IINC 9 1
    GOTO L13
   L33
   L18
    LINENUMBER 155 L18
   FRAME FULL [[Ljava/lang/String; edu/columbia/cs/psl/phosphor/struct/ControlTaintTagStack edu/columbia/cs/psl/phosphor/struct/EnqueuedTaint edu/columbia/cs/psl/phosphor/struct/EnqueuedTaint edu/columbia/cs/psl/phosphor/struct/EnqueuedTaint edu/columbia/cs/psl/phosphor/struct/TaintedBooleanWithObjTag] []
    ALOAD 1
    ALOAD 2
    INVOKEVIRTUAL edu/columbia/cs/psl/phosphor/struct/ControlTaintTagStack.pop (Ledu/columbia/cs/psl/phosphor/struct/EnqueuedTaint;)V
    ALOAD 1
    ALOAD 3
    INVOKEVIRTUAL edu/columbia/cs/psl/phosphor/struct/ControlTaintTagStack.pop (Ledu/columbia/cs/psl/phosphor/struct/EnqueuedTaint;)V
    RETURN
   L34
    LOCALVARIABLE e Ljava/lang/IllegalAccessException; L26 L27 13
   L35
    LOCALVARIABLE phosphorJumpControlTag2 Ledu/columbia/cs/psl/phosphor/struct/EnqueuedTaint; L1 L35 3
    LOCALVARIABLE phosphorJumpControlTag1 Ledu/columbia/cs/psl/phosphor/struct/EnqueuedTaint; L1 L35 2
    LOCALVARIABLE phosphorShadowLVFor9XX2 Ledu/columbia/cs/psl/phosphor/runtime/Taint; L12 L14 10
    LOCALVARIABLE phosphorShadowLV4 Ledu/columbia/cs/psl/phosphor/runtime/Taint; L15 L35 8
    LOCALVARIABLE phosphorJumpControlTag0 Ledu/columbia/cs/psl/phosphor/struct/ControlTaintTagStack; L1 L35 1
    LOCALVARIABLE phosphorShadowLVFor7XX1 Ledu/columbia/cs/psl/phosphor/runtime/Taint; L11 L15 8
    LOCALVARIABLE phosphorShadowLV5 I L16 L17 11
    LOCALVARIABLE phosphorJumpControlTag3 Ledu/columbia/cs/psl/phosphor/struct/EnqueuedTaint; L1 L35 4
    LOCALVARIABLE phosphorShadowLV3 Ledu/columbia/cs/psl/phosphor/runtime/Taint; L14 L35 10
    LOCALVARIABLE phosphorReturnPreAlloc0 Ledu/columbia/cs/psl/phosphor/struct/TaintedBooleanWithObjTag; L3 L35 5
    LOCALVARIABLE e Ljava/lang/IllegalArgumentException; L29 L30 13
    LOCALVARIABLE e Ljava/lang/reflect/InvocationTargetException; L32 L21 13
    LOCALVARIABLE m Ljava/lang/reflect/Method; L20 L21 12
    LOCALVARIABLE args [Ljava/lang/String; L10 L34 0
    MAXSTACK = 103
    MAXLOCALS = 14

  // access flags 0x8
  static <clinit>()V
   L0
   L1
    NEW edu/columbia/cs/psl/phosphor/struct/ControlTaintTagStack
    DUP
    BIPUSH 1
    INVOKESPECIAL edu/columbia/cs/psl/phosphor/struct/ControlTaintTagStack.<init> (I)V
    ASTORE 0
    ACONST_NULL
    ASTORE 1
   L2
   L3
    NEW edu/columbia/cs/psl/phosphor/struct/TaintedBooleanWithObjTag
    DUP
    INVOKESPECIAL edu/columbia/cs/psl/phosphor/struct/TaintedBooleanWithObjTag.<init> ()V
    ASTORE 2
   L4
   L5
    LINENUMBER 12 L5
    LDC Lcom/josecambronero/ObjectTagExamples;.class
    ALOAD 2
    INVOKEVIRTUAL java/lang/Class.desiredAssertionStatus$$PHOSPHORTAGGED (Ledu/columbia/cs/psl/phosphor/struct/TaintedBooleanWithObjTag;)Ledu/columbia/cs/psl/phosphor/struct/TaintedBooleanWithObjTag;
    DUP
    GETFIELD edu/columbia/cs/psl/phosphor/struct/TaintedBooleanWithObjTag.taint : Ledu/columbia/cs/psl/phosphor/runtime/Taint;
    SWAP
    GETFIELD edu/columbia/cs/psl/phosphor/struct/TaintedBooleanWithObjTag.val : Z
    DUP
    INVOKESTATIC edu/ucdavis/cs/cyberlab/BBPhosphor/util/TaintHelper.saveTaint (Ljava/lang/Object;)V
    LDC "hello i coupied this! branching counting 1"
    INVOKESTATIC edu/ucdavis/cs/cyberlab/BBPhosphor/util/TaintHelper.printx (Ljava/lang/String;)V
    SWAP
    ALOAD 0
    SWAP
    ALOAD 1
    INVOKEVIRTUAL edu/columbia/cs/psl/phosphor/struct/ControlTaintTagStack.push (Ledu/columbia/cs/psl/phosphor/runtime/Taint;Ledu/columbia/cs/psl/phosphor/struct/EnqueuedTaint;)Ledu/columbia/cs/psl/phosphor/struct/EnqueuedTaint;
    ASTORE 1
    IFNE L6
   L7
    ALOAD 0
    INVOKEVIRTUAL edu/columbia/cs/psl/phosphor/struct/ControlTaintTagStack.copyTag ()Ledu/columbia/cs/psl/phosphor/runtime/Taint;
    ICONST_1
    GOTO L8
   L9
   L6
   FRAME FULL [edu/columbia/cs/psl/phosphor/struct/ControlTaintTagStack edu/columbia/cs/psl/phosphor/struct/EnqueuedTaint edu/columbia/cs/psl/phosphor/struct/TaintedBooleanWithObjTag] []
    ALOAD 0
    INVOKEVIRTUAL edu/columbia/cs/psl/phosphor/struct/ControlTaintTagStack.copyTag ()Ledu/columbia/cs/psl/phosphor/runtime/Taint;
    ICONST_0
   L8
   FRAME FULL [edu/columbia/cs/psl/phosphor/struct/ControlTaintTagStack edu/columbia/cs/psl/phosphor/struct/EnqueuedTaint edu/columbia/cs/psl/phosphor/struct/TaintedBooleanWithObjTag] [edu/columbia/cs/psl/phosphor/runtime/Taint I]
    ALOAD 0
    ALOAD 1
    INVOKEVIRTUAL edu/columbia/cs/psl/phosphor/struct/ControlTaintTagStack.pop (Ledu/columbia/cs/psl/phosphor/struct/EnqueuedTaint;)V
    SWAP
    ALOAD 0
    INVOKESTATIC edu/columbia/cs/psl/phosphor/runtime/Taint.combineTags (Ledu/columbia/cs/psl/phosphor/runtime/Taint;Ledu/columbia/cs/psl/phosphor/struct/ControlTaintTagStack;)Ledu/columbia/cs/psl/phosphor/runtime/Taint;
    SWAP
    PUTSTATIC com/josecambronero/ObjectTagExamples.$assertionsDisabled : Z
    PUTSTATIC com/josecambronero/ObjectTagExamples.$assertionsDisabledPHOSPHOR_TAG : Ledu/columbia/cs/psl/phosphor/runtime/Taint;
    RETURN
   L10
    MAXSTACK = 101
    MAXLOCALS = 3

  // access flags 0x18
  final static J serialVersionUID = -3753243394819980034

  // access flags 0x1
  public Ledu/columbia/cs/psl/phosphor/runtime/Taint; PHOSPHOR_TAG

  // access flags 0x1009
  public static synthetic Ledu/columbia/cs/psl/phosphor/runtime/Taint; $assertionsDisabledPHOSPHOR_TAG

  // access flags 0x9
  public static Ledu/columbia/cs/psl/phosphor/runtime/Taint; serialVersionUIDPHOSPHOR_TAG

  // access flags 0x1
  public equals(Ljava/lang/Object;)Z
   L0
    ALOAD 0
    ALOAD 1
    INVOKESPECIAL java/lang/Object.equals (Ljava/lang/Object;)Z
   L1
    IRETURN
    LOCALVARIABLE this Lcom/josecambronero/ObjectTagExamples; L0 L1 0
    LOCALVARIABLE other Ljava/lang/Object; L0 L1 1
    MAXSTACK = 0
    MAXLOCALS = 0

  // access flags 0x1
  public hashCode()I
   L0
    ALOAD 0
    INVOKESPECIAL java/lang/Object.hashCode ()I
   L1
    IRETURN
    LOCALVARIABLE this Lcom/josecambronero/ObjectTagExamples; L0 L1 0
    MAXSTACK = 0
    MAXLOCALS = 0

  // access flags 0x1
  public getPHOSPHOR_TAG()Ljava/lang/Object;
    ALOAD 0
    GETFIELD com/josecambronero/ObjectTagExamples.PHOSPHOR_TAG : Ledu/columbia/cs/psl/phosphor/runtime/Taint;
    ARETURN
    MAXSTACK = 0
    MAXLOCALS = 0

  // access flags 0x1
  public setPHOSPHOR_TAG(Ljava/lang/Object;)V
    ALOAD 0
    ALOAD 1
    CHECKCAST edu/columbia/cs/psl/phosphor/runtime/Taint
    PUTFIELD com/josecambronero/ObjectTagExamples.PHOSPHOR_TAG : Ledu/columbia/cs/psl/phosphor/runtime/Taint;
    RETURN
    MAXSTACK = 0
    MAXLOCALS = 0

  // access flags 0x1
  public equals$$PHOSPHORTAGGED(Ljava/lang/Object;Ledu/columbia/cs/psl/phosphor/struct/TaintedBooleanWithObjTag;)Ledu/columbia/cs/psl/phosphor/struct/TaintedBooleanWithObjTag;
   L0
   L1
    ALOAD 0
    ALOAD 1
    DUP
    DUP
    INSTANCEOF [Ledu/columbia/cs/psl/phosphor/struct/LazyArrayObjTags;
    SWAP
    INSTANCEOF edu/columbia/cs/psl/phosphor/struct/LazyArrayObjTags
    IOR
    IFEQ L2
    INVOKESTATIC edu/columbia/cs/psl/phosphor/struct/multid/MultiDTaintedArrayWithObjTag.unboxRaw (Ljava/lang/Object;)Ljava/lang/Object;
   L2
   FRAME FULL [com/josecambronero/ObjectTagExamples java/lang/Object edu/columbia/cs/psl/phosphor/struct/TaintedBooleanWithObjTag] [com/josecambronero/ObjectTagExamples java/lang/Object]
    INVOKESPECIAL com/josecambronero/ObjectTagExamples.equals (Ljava/lang/Object;)Z
    ALOAD 2
    SWAP
    PUTFIELD edu/columbia/cs/psl/phosphor/struct/TaintedBooleanWithObjTag.val : Z
    ALOAD 2
    ACONST_NULL
    PUTFIELD edu/columbia/cs/psl/phosphor/struct/TaintedBooleanWithObjTag.taint : Ledu/columbia/cs/psl/phosphor/runtime/Taint;
    ALOAD 2
   L3
    ARETURN
    LOCALVARIABLE this Lcom/josecambronero/ObjectTagExamples; L1 L3 0
    LOCALVARIABLE phosphorNativeWrapArg1 Ljava/lang/Object; L1 L3 1
    LOCALVARIABLE phosphorReturnHolder Ledu/columbia/cs/psl/phosphor/struct/TaintedBooleanWithObjTag; L1 L3 2
   L4
    MAXSTACK = 4
    MAXLOCALS = 3

  // access flags 0x1
  public hashCode$$PHOSPHORTAGGED(Ledu/columbia/cs/psl/phosphor/struct/TaintedIntWithObjTag;)Ledu/columbia/cs/psl/phosphor/struct/TaintedIntWithObjTag;
   L0
   L1
    ALOAD 0
    INVOKESPECIAL com/josecambronero/ObjectTagExamples.hashCode ()I
    ALOAD 1
    SWAP
    PUTFIELD edu/columbia/cs/psl/phosphor/struct/TaintedIntWithObjTag.val : I
    ALOAD 1
    ACONST_NULL
    PUTFIELD edu/columbia/cs/psl/phosphor/struct/TaintedIntWithObjTag.taint : Ledu/columbia/cs/psl/phosphor/runtime/Taint;
    ALOAD 1
   L2
    ARETURN
    LOCALVARIABLE this Lcom/josecambronero/ObjectTagExamples; L1 L2 0
    LOCALVARIABLE phosphorReturnHolder Ledu/columbia/cs/psl/phosphor/struct/TaintedIntWithObjTag; L1 L2 1
   L3
    MAXSTACK = 2
    MAXLOCALS = 2

  // access flags 0x1
  public getClass$$PHOSPHORTAGGED()Ljava/lang/Class;
   L0
   L1
    ALOAD 0
    INVOKESPECIAL com/josecambronero/ObjectTagExamples.getClass ()Ljava/lang/Class;
   L2
    ARETURN
    LOCALVARIABLE this Lcom/josecambronero/ObjectTagExamples; L1 L2 0
   L3
    MAXSTACK = 1
    MAXLOCALS = 1

  // access flags 0x1
  public toString$$PHOSPHORTAGGED()Ljava/lang/String;
   L0
   L1
    ALOAD 0
    INVOKESPECIAL com/josecambronero/ObjectTagExamples.toString ()Ljava/lang/String;
   L2
    ARETURN
    LOCALVARIABLE this Lcom/josecambronero/ObjectTagExamples; L1 L2 0
   L3
    MAXSTACK = 1
    MAXLOCALS = 1
}
